{"parse": {"title": "The Hobbit", "pageid": 2877, "redirects": [{"from": "Hobbitus Ille", "to": "The Hobbit"}], "links": [{"ns": 6, "exists": "", "*": "File:The Hobbit 2016-facsimile.jpeg"}, {"ns": 6, "exists": "", "*": "File:J.R.R. Tolkien - Thror's map.jpg"}, {"ns": 6, "exists": "", "*": "File:J.R.R. Tolkien - Map of Wilderland.jpg"}, {"ns": 6, "exists": "", "*": "File:J.R.R. Tolkien - The Trolls.png"}, {"ns": 6, "exists": "", "*": "File:J.R.R. Tolkien - The Mountain-path.jpg"}, {"ns": 6, "exists": "", "*": "File:J.R.R. Tolkien - The Misty Mountains looking West from the Eyrie towards Goblin Gate.jpg"}, {"ns": 6, "exists": "", "*": "File:J.R.R. Tolkien - Beorn's Hall.jpg"}, {"ns": 6, "exists": "", "*": "File:J.R.R. Tolkien - The Elvenking's Gate (II).jpg"}, {"ns": 6, "exists": "", "*": "File:J.R.R. Tolkien - Lake Town.jpg"}, {"ns": 6, "exists": "", "*": "File:J.R.R. Tolkien - The Front Gate.png"}, {"ns": 6, "exists": "", "*": "File:J.R.R. Tolkien - The Hall at Bag-End.jpg"}, {"ns": 6, "exists": "", "*": "File:The Hobbit (dramatised by Patricia Gray).png"}, {"ns": 0, "exists": "", "*": "13 April"}, {"ns": 0, "exists": "", "*": "15 December"}, {"ns": 0, "exists": "", "*": "16 July"}, {"ns": 0, "exists": "", "*": "17 January"}, {"ns": 0, "exists": "", "*": "1937"}, {"ns": 0, "exists": "", "*": "1938"}, {"ns": 0, "exists": "", "*": "1964"}, {"ns": 0, "exists": "", "*": "1967"}, {"ns": 0, "exists": "", "*": "1968"}, {"ns": 0, "exists": "", "*": "1977"}, {"ns": 0, "exists": "", "*": "1982"}, {"ns": 0, "exists": "", "*": "1985"}, {"ns": 0, "exists": "", "*": "1989"}, {"ns": 0, "exists": "", "*": "21 September"}, {"ns": 0, "exists": "", "*": "27 November"}, {"ns": 0, "exists": "", "*": "31 August"}, {"ns": 0, "exists": "", "*": "4 February"}, {"ns": 0, "exists": "", "*": "4 January"}, {"ns": 0, "exists": "", "*": "5 February"}, {"ns": 0, "exists": "", "*": "8 February"}, {"ns": 0, "exists": "", "*": "A Companion to J.R.R. Tolkien"}, {"ns": 0, "exists": "", "*": "A Middle English Reader and Vocabulary"}, {"ns": 0, "exists": "", "*": "A Secret Vice: Tolkien on Invented Languages"}, {"ns": 0, "exists": "", "*": "A Short Rest"}, {"ns": 0, "exists": "", "*": "A Thief in the Night"}, {"ns": 0, "exists": "", "*": "A Warm Welcome"}, {"ns": 0, "exists": "", "*": "Alan Lee"}, {"ns": 0, "exists": "", "*": "Allen & Unwin"}, {"ns": 0, "exists": "", "*": "An Unexpected Party"}, {"ns": 0, "exists": "", "*": "Ancrene Wisse"}, {"ns": 0, "exists": "", "*": "Anthony Jackson"}, {"ns": 0, "exists": "", "*": "Aragorn"}, {"ns": 0, "exists": "", "*": "Arda"}, {"ns": 0, "exists": "", "*": "Arkenstone"}, {"ns": 0, "exists": "", "*": "Azog"}, {"ns": 0, "exists": "", "*": "BBC"}, {"ns": 0, "exists": "", "*": "Back Door"}, {"ns": 0, "exists": "", "*": "Bag End"}, {"ns": 0, "exists": "", "*": "Bain"}, {"ns": 0, "exists": "", "*": "Balin"}, {"ns": 0, "exists": "", "*": "Bandobras Took"}, {"ns": 0, "exists": "", "*": "Barbara Remington"}, {"ns": 0, "exists": "", "*": "Bard"}, {"ns": 0, "exists": "", "*": "Barrels Out of Bond"}, {"ns": 0, "exists": "", "*": "Battle of Five Armies"}, {"ns": 0, "exists": "", "*": "Belladonna Took"}, {"ns": 0, "exists": "", "*": "Beorn"}, {"ns": 0, "exists": "", "*": "Beowulf: A Translation and Commentary"}, {"ns": 0, "exists": "", "*": "Beowulf (poem)"}, {"ns": 0, "exists": "", "*": "Beowulf and the Critics"}, {"ns": 0, "exists": "", "*": "Beren and Lúthien"}, {"ns": 0, "exists": "", "*": "Bert"}, {"ns": 0, "exists": "", "*": "Bifur"}, {"ns": 0, "exists": "", "*": "Bilbo's Last Song (at the Grey Havens)"}, {"ns": 0, "exists": "", "*": "Bilbo Baggins"}, {"ns": 0, "exists": "", "*": "Bofur"}, {"ns": 0, "exists": "", "*": "Bolg"}, {"ns": 0, "exists": "", "*": "Bombur"}, {"ns": 0, "exists": "", "*": "Boromir"}, {"ns": 0, "exists": "", "*": "Brobdingnagian Bards"}, {"ns": 0, "exists": "", "*": "Bungo Baggins"}, {"ns": 0, "exists": "", "*": "C.S. Lewis"}, {"ns": 0, "exists": "", "*": "Carc"}, {"ns": 0, "exists": "", "*": "Celeborn"}, {"ns": 0, "exists": "", "*": "Christina Scull"}, {"ns": 0, "exists": "", "*": "Christopher Tolkien"}, {"ns": 0, "exists": "", "*": "Cirth"}, {"ns": 0, "exists": "", "*": "Councillors"}, {"ns": 0, "exists": "", "*": "David T. Wenzel"}, {"ns": 0, "exists": "", "*": "Denethor"}, {"ns": 0, "exists": "", "*": "Denis Gordeev"}, {"ns": 0, "exists": "", "*": "Donato Giancola"}, {"ns": 0, "exists": "", "*": "Dori"}, {"ns": 0, "exists": "", "*": "Douglas A. Anderson"}, {"ns": 0, "exists": "", "*": "Durin"}, {"ns": 0, "exists": "", "*": "Dwalin"}, {"ns": 0, "exists": "", "*": "Dwarves"}, {"ns": 0, "exists": "", "*": "Dáin Ironfoot"}, {"ns": 0, "exists": "", "*": "Elaine Griffiths"}, {"ns": 0, "exists": "", "*": "Elrond"}, {"ns": 0, "exists": "", "*": "Enya"}, {"ns": 0, "exists": "", "*": "Faramir"}, {"ns": 0, "exists": "", "*": "Farmer Giles of Ham"}, {"ns": 0, "exists": "", "*": "Finn and Hengest: The Fragment and the Episode"}, {"ns": 0, "exists": "", "*": "Fire and Water"}, {"ns": 0, "exists": "", "*": "Flies and Spiders"}, {"ns": 0, "exists": "", "*": "Frodo Baggins"}, {"ns": 0, "exists": "", "*": "Fíli"}, {"ns": 0, "exists": "", "*": "Galadriel"}, {"ns": 0, "exists": "", "*": "Galion"}, {"ns": 0, "exists": "", "*": "Gandalf"}, {"ns": 0, "exists": "", "*": "Gene Deitch"}, {"ns": 0, "exists": "", "*": "George Allen & Unwin"}, {"ns": 0, "exists": "", "*": "Gerontius Took"}, {"ns": 0, "exists": "", "*": "Gimli"}, {"ns": 0, "exists": "", "*": "Girion"}, {"ns": 0, "exists": "", "*": "Glóin"}, {"ns": 0, "exists": "", "*": "Goblin-town"}, {"ns": 0, "exists": "", "*": "Goblins"}, {"ns": 0, "exists": "", "*": "Golfimbul"}, {"ns": 0, "exists": "", "*": "Gollum"}, {"ns": 0, "exists": "", "*": "Gollum's Song"}, {"ns": 0, "exists": "", "*": "Gollum: How We Made Movie Magic"}, {"ns": 0, "exists": "", "*": "Gondolin"}, {"ns": 0, "exists": "", "*": "Great Eagle"}, {"ns": 0, "exists": "", "*": "Great Goblin"}, {"ns": 0, "exists": "", "*": "Grishnákh"}, {"ns": 0, "exists": "", "*": "Gríma"}, {"ns": 0, "exists": "", "*": "H.E. Riddett"}, {"ns": 0, "exists": "", "*": "Haldir"}, {"ns": 0, "exists": "", "*": "Heron Carvic"}, {"ns": 0, "exists": "", "*": "Hobbit"}, {"ns": 0, "exists": "", "*": "Houghton Mifflin"}, {"ns": 0, "exists": "", "*": "Humphrey Carpenter"}, {"ns": 0, "exists": "", "*": "I See Fire"}, {"ns": 0, "exists": "", "*": "Inside Information"}, {"ns": 0, "exists": "", "*": "Into the West"}, {"ns": 0, "exists": "", "*": "Iron Hills"}, {"ns": 0, "exists": "", "*": "J.R.R. Tolkien"}, {"ns": 0, "exists": "", "*": "J.R.R. Tolkien: A Biography"}, {"ns": 0, "exists": "", "*": "J.R.R. Tolkien: Artist and Illustrator"}, {"ns": 0, "exists": "", "*": "J.R.R. Tolkien: Life and Legend"}, {"ns": 0, "exists": "", "*": "J.R.R. Tolkien: The Art of the Manuscript"}, {"ns": 0, "exists": "", "*": "January"}, {"ns": 0, "exists": "", "*": "Jemima Catlin"}, {"ns": 0, "exists": "", "*": "John D. Rateliff"}, {"ns": 0, "exists": "", "*": "John Howe"}, {"ns": 0, "exists": "", "*": "John Tolkien"}, {"ns": 0, "exists": "", "*": "Kíli"}, {"ns": 0, "exists": "", "*": "Lake-town"}, {"ns": 0, "exists": "", "*": "Leaf by Niggle"}, {"ns": 0, "exists": "", "*": "Led Zeppelin"}, {"ns": 0, "exists": "", "*": "Legendarium"}, {"ns": 0, "exists": "", "*": "Lego The Hobbit: The Video Game"}, {"ns": 0, "exists": "", "*": "Lego The Lord of the Rings: The Video Game"}, {"ns": 0, "exists": "", "*": "Legolas"}, {"ns": 0, "exists": "", "*": "Leonard Nimoy"}, {"ns": 0, "exists": "", "*": "Letter 10"}, {"ns": 0, "exists": "", "*": "Letter 11"}, {"ns": 0, "exists": "", "*": "Letter 12"}, {"ns": 0, "exists": "", "*": "Letter 15"}, {"ns": 0, "exists": "", "*": "Letter 163"}, {"ns": 0, "exists": "", "*": "Letter 22"}, {"ns": 0, "exists": "", "*": "Letter 257"}, {"ns": 0, "exists": "", "*": "Letter 294"}, {"ns": 0, "exists": "", "*": "Letter 9"}, {"ns": 0, "exists": "", "*": "Letters from Father Christmas"}, {"ns": 0, "exists": "", "*": "Lonely Mountain"}, {"ns": 0, "exists": "", "*": "Lurtz"}, {"ns": 0, "exists": "", "*": "Master of Lake-town"}, {"ns": 0, "exists": "", "*": "May It Be"}, {"ns": 0, "exists": "", "*": "Meriadoc Brandybuck"}, {"ns": 0, "exists": "", "*": "Michael Hague"}, {"ns": 0, "exists": "", "*": "Middle-earth"}, {"ns": 0, "exists": "", "*": "Mirkwood"}, {"ns": 0, "exists": "", "*": "Misty Mountains"}, {"ns": 0, "exists": "", "*": "Morgoth's Ring"}, {"ns": 0, "exists": "", "*": "Mr. Bliss"}, {"ns": 0, "exists": "", "*": "New Zealand"}, {"ns": 0, "exists": "", "*": "Nori"}, {"ns": 0, "exists": "", "*": "Not at Home"}, {"ns": 0, "exists": "", "*": "Old English"}, {"ns": 0, "exists": "", "*": "On the Doorstep"}, {"ns": 0, "exists": "", "*": "One Ring"}, {"ns": 0, "exists": "", "*": "Ori"}, {"ns": 0, "exists": "", "*": "Out of the Frying-Pan into the Fire"}, {"ns": 0, "exists": "", "*": "Over Hill and Under Hill"}, {"ns": 0, "exists": "", "*": "Parma Eldalamberon"}, {"ns": 0, "exists": "", "*": "Paul Daneman"}, {"ns": 0, "exists": "", "*": "Pauline Baynes"}, {"ns": 0, "exists": "", "*": "Pembroke College"}, {"ns": 0, "exists": "", "*": "Peregrin Took"}, {"ns": 0, "exists": "", "*": "Peter Jackson"}, {"ns": 0, "exists": "", "*": "Pictures by J.R.R. Tolkien"}, {"ns": 0, "exists": "", "*": "Poems from The Hobbit"}, {"ns": 0, "exists": "", "*": "Poems in The Hobbit"}, {"ns": 0, "exists": "", "*": "Queer Lodgings"}, {"ns": 0, "exists": "", "*": "Radagast"}, {"ns": 0, "exists": "", "*": "Rankin/Bass"}, {"ns": 0, "exists": "", "*": "Rayner Unwin"}, {"ns": 0, "exists": "", "*": "Red Book of Westmarch"}, {"ns": 0, "exists": "", "*": "Return to Bag-End"}, {"ns": 0, "exists": "", "*": "Riddles in the Dark"}, {"ns": 0, "exists": "", "*": "Rivendell"}, {"ns": 0, "exists": "", "*": "Roast Mutton"}, {"ns": 0, "exists": "", "*": "Roger Garland"}, {"ns": 0, "exists": "", "*": "Roverandom"}, {"ns": 0, "exists": "", "*": "Roäc"}, {"ns": 0, "exists": "", "*": "Runes"}, {"ns": 0, "exists": "", "*": "Samwise Gamgee"}, {"ns": 0, "exists": "", "*": "Saruman"}, {"ns": 0, "exists": "", "*": "Sauron"}, {"ns": 0, "exists": "", "*": "Sauron Defeated"}, {"ns": 0, "exists": "", "*": "Sharku"}, {"ns": 0, "exists": "", "*": "Sigrid"}, {"ns": 0, "exists": "", "*": "Sir Gawain and the Green Knight, Pearl, and Sir Orfeo"}, {"ns": 0, "exists": "", "*": "Sir Gawain and the Green Knight (edition)"}, {"ns": 0, "exists": "", "*": "Smaug"}, {"ns": 0, "exists": "", "*": "Smaug: Unleashing the Dragon"}, {"ns": 0, "exists": "", "*": "Smith of Wootton Major"}, {"ns": 0, "exists": "", "*": "Song of the Lonely Mountain"}, {"ns": 0, "exists": "", "*": "Sunday"}, {"ns": 0, "exists": "", "*": "Tales from the Perilous Realm"}, {"ns": 0, "exists": "", "*": "Tauriel"}, {"ns": 0, "exists": "", "*": "Ted Nasmith"}, {"ns": 0, "exists": "", "*": "The 1960 Hobbit"}, {"ns": 0, "exists": "", "*": "The Adventures of Tom Bombadil"}, {"ns": 0, "exists": "", "*": "The Annotated Hobbit"}, {"ns": 0, "exists": "", "*": "The Art of The Fellowship of the Ring"}, {"ns": 0, "exists": "", "*": "The Art of The Hobbit"}, {"ns": 0, "exists": "", "*": "The Art of The Lord of the Rings"}, {"ns": 0, "exists": "", "*": "The Art of The Lord of the Rings (film book)"}, {"ns": 0, "exists": "", "*": "The Art of The Return of the King"}, {"ns": 0, "exists": "", "*": "The Art of The Two Towers"}, {"ns": 0, "exists": "", "*": "The Battle of Maldon: together with The Homecoming of Beorhtnoth"}, {"ns": 0, "exists": "", "*": "The Book of Lost Tales"}, {"ns": 0, "exists": "", "*": "The Book of Lost Tales: Part One"}, {"ns": 0, "exists": "", "*": "The Book of Lost Tales: Part Two"}, {"ns": 0, "exists": "", "*": "The Bovadium Fragments: together with The Origin of Bovadium"}, {"ns": 0, "exists": "", "*": "The Children of Húrin"}, {"ns": 0, "exists": "", "*": "The Chronology of The Lord of the Rings"}, {"ns": 0, "exists": "", "*": "The Clouds Burst"}, {"ns": 0, "exists": "", "*": "The Collected Poems of J.R.R. Tolkien"}, {"ns": 0, "exists": "", "*": "The Complete Guide to Middle-earth"}, {"ns": 0, "exists": "", "*": "The Fall of Arthur"}, {"ns": 0, "exists": "", "*": "The Fall of Gondolin"}, {"ns": 0, "exists": "", "*": "The Fall of Númenor"}, {"ns": 0, "exists": "", "*": "The Fellowship of the Ring"}, {"ns": 0, "exists": "", "*": "The Folio Society"}, {"ns": 0, "exists": "", "*": "The Gathering of the Clouds"}, {"ns": 0, "exists": "", "*": "The Great Tales Never End"}, {"ns": 0, "exists": "", "*": "The History of Middle-earth"}, {"ns": 0, "exists": "", "*": "The History of Middle-earth Index"}, {"ns": 0, "exists": "", "*": "The History of The Hobbit"}, {"ns": 0, "exists": "", "*": "The Hobbit/Publication history and gallery"}, {"ns": 0, "exists": "", "*": "The Hobbit/Translations"}, {"ns": 0, "exists": "", "*": "The Hobbit: An Unexpected Journey"}, {"ns": 0, "exists": "", "*": "The Hobbit: An Unexpected Journey: Annual 2013"}, {"ns": 0, "exists": "", "*": "The Hobbit: An Unexpected Journey: Chronicles: Art & Design"}, {"ns": 0, "exists": "", "*": "The Hobbit: An Unexpected Journey: Chronicles: Creatures & Characters"}, {"ns": 0, "exists": "", "*": "The Hobbit: An Unexpected Journey: Official Movie Guide"}, {"ns": 0, "exists": "", "*": "The Hobbit: An Unexpected Journey: The Movie Storybook"}, {"ns": 0, "exists": "", "*": "The Hobbit: An Unexpected Journey: The World of Hobbits"}, {"ns": 0, "exists": "", "*": "The Hobbit: An Unexpected Journey: Visual Companion"}, {"ns": 0, "exists": "", "*": "The Hobbit: An Unexpected Journey (extended edition)"}, {"ns": 0, "exists": "", "*": "The Hobbit: An Unexpected Journey - Original Motion Picture Soundtrack"}, {"ns": 0, "exists": "", "*": "The Hobbit: An Unexpected Journey - Original Motion Picture Soundtrack - Special Edition"}, {"ns": 0, "exists": "", "*": "The Hobbit: Armies of The Third Age"}, {"ns": 0, "exists": "", "*": "The Hobbit: Kingdoms of Middle-earth"}, {"ns": 0, "exists": "", "*": "The Hobbit: The Battle of the Five Armies"}, {"ns": 0, "exists": "", "*": "The Hobbit: The Battle of the Five Armies: Activity Book"}, {"ns": 0, "exists": "", "*": "The Hobbit: The Battle of the Five Armies: Annual 2015"}, {"ns": 0, "exists": "", "*": "The Hobbit: The Battle of the Five Armies: Chronicles: Art & Design"}, {"ns": 0, "exists": "", "*": "The Hobbit: The Battle of the Five Armies: Chronicles: The Art of War"}, {"ns": 0, "exists": "", "*": "The Hobbit: The Battle of the Five Armies: Official Movie Guide"}, {"ns": 0, "exists": "", "*": "The Hobbit: The Battle of the Five Armies: The Movie Storybook"}, {"ns": 0, "exists": "", "*": "The Hobbit: The Battle of the Five Armies: Visual Companion"}, {"ns": 0, "exists": "", "*": "The Hobbit: The Battle of the Five Armies (extended edition)"}, {"ns": 0, "exists": "", "*": "The Hobbit: The Battle of the Five Armies - Original Motion Picture Soundtrack"}, {"ns": 0, "exists": "", "*": "The Hobbit: The Battle of the Five Armies - Original Motion Picture Soundtrack - Special Edition"}, {"ns": 0, "exists": "", "*": "The Hobbit: The Desolation of Smaug"}, {"ns": 0, "exists": "", "*": "The Hobbit: The Desolation of Smaug: Activity Book"}, {"ns": 0, "exists": "", "*": "The Hobbit: The Desolation of Smaug: Annual 2014"}, {"ns": 0, "exists": "", "*": "The Hobbit: The Desolation of Smaug: Chronicles: Art & Design"}, {"ns": 0, "exists": "", "*": "The Hobbit: The Desolation of Smaug: Chronicles: Cloaks & Daggers"}, {"ns": 0, "exists": "", "*": "The Hobbit: The Desolation of Smaug: Official Movie Guide"}, {"ns": 0, "exists": "", "*": "The Hobbit: The Desolation of Smaug: Sticker Book"}, {"ns": 0, "exists": "", "*": "The Hobbit: The Desolation of Smaug: The Movie Storybook"}, {"ns": 0, "exists": "", "*": "The Hobbit: The Desolation of Smaug: Ultimate Sticker Collection"}, {"ns": 0, "exists": "", "*": "The Hobbit: The Desolation of Smaug: Visual Companion"}, {"ns": 0, "exists": "", "*": "The Hobbit: The Desolation of Smaug (extended edition)"}, {"ns": 0, "exists": "", "*": "The Hobbit: The Desolation of Smaug - Original Motion Picture Soundtrack"}, {"ns": 0, "exists": "", "*": "The Hobbit: The Desolation of Smaug - Original Motion Picture Soundtrack - Special Edition"}, {"ns": 0, "exists": "", "*": "The Hobbit (1967 film)"}, {"ns": 0, "exists": "", "*": "The Hobbit (1968 radio series)"}, {"ns": 0, "exists": "", "*": "The Hobbit (1977 film)"}, {"ns": 0, "exists": "", "*": "The Hobbit (1982 video game)"}, {"ns": 0, "exists": "", "*": "The Hobbit (1985 television film)"}, {"ns": 0, "exists": "", "*": "The Hobbit (2003 video game)"}, {"ns": 0, "exists": "", "*": "The Hobbit (comic book)"}, {"ns": 0, "exists": "", "*": "The Hobbit (disambiguation)"}, {"ns": 0, "exists": "", "*": "The Hobbit (film series)"}, {"ns": 0, "exists": "", "*": "The Hobbit 1st edition"}, {"ns": 0, "exists": "", "*": "The Hobbit Motion Picture Trilogy Location Guide: Hobbiton, the Lonely Mountain and Beyond"}, {"ns": 0, "exists": "", "*": "The Hobbit Preface"}, {"ns": 0, "exists": "", "*": "The Hobbit Sketchbook"}, {"ns": 0, "exists": "", "*": "The Hobbit Trilogy Location Guidebook"}, {"ns": 0, "exists": "", "*": "The Inklings (book)"}, {"ns": 0, "exists": "", "*": "The J.R.R. Tolkien Companion and Guide"}, {"ns": 0, "exists": "", "*": "The Keys of Middle-earth"}, {"ns": 0, "exists": "", "*": "The Last Goodbye"}, {"ns": 0, "exists": "", "*": "The Last Stage"}, {"ns": 0, "exists": "", "*": "The Lay of Aotrou and Itroun"}, {"ns": 0, "exists": "", "*": "The Lays of Beleriand"}, {"ns": 0, "exists": "", "*": "The Legend of Sigurd and Gudrún"}, {"ns": 0, "exists": "", "*": "The Letters of J.R.R. Tolkien"}, {"ns": 0, "exists": "", "*": "The Lord of the Rings"}, {"ns": 0, "exists": "", "*": "The Lord of the Rings: A Reader's Companion"}, {"ns": 0, "exists": "", "*": "The Lord of the Rings: Aragorn's Quest"}, {"ns": 0, "exists": "", "*": "The Lord of the Rings: Conquest"}, {"ns": 0, "exists": "", "*": "The Lord of the Rings: Official Movie Guide"}, {"ns": 0, "exists": "", "*": "The Lord of the Rings: Tactics"}, {"ns": 0, "exists": "", "*": "The Lord of the Rings: The Fellowship of the Ring"}, {"ns": 0, "exists": "", "*": "The Lord of the Rings: The Fellowship of the Ring (extended edition)"}, {"ns": 0, "exists": "", "*": "The Lord of the Rings: The Fellowship of the Ring - Original Motion Picture Soundtrack"}, {"ns": 0, "exists": "", "*": "The Lord of the Rings: The Fellowship of the Ring - The Complete Recordings"}, {"ns": 0, "exists": "", "*": "The Lord of the Rings: The Fellowship of the Ring Photo Guide"}, {"ns": 0, "exists": "", "*": "The Lord of the Rings: The Fellowship of the Ring Visual Companion"}, {"ns": 0, "exists": "", "*": "The Lord of the Rings: The Fellowship of the Rings - Insiders' Guide"}, {"ns": 0, "exists": "", "*": "The Lord of the Rings: The Making of the Movie Trilogy"}, {"ns": 0, "exists": "", "*": "The Lord of the Rings: The Return of the King"}, {"ns": 0, "exists": "", "*": "The Lord of the Rings: The Return of the King (extended edition)"}, {"ns": 0, "exists": "", "*": "The Lord of the Rings: The Return of the King (video game)"}, {"ns": 0, "exists": "", "*": "The Lord of the Rings: The Return of the King - Original Motion Picture Soundtrack"}, {"ns": 0, "exists": "", "*": "The Lord of the Rings: The Return of the King - The Complete Recordings"}, {"ns": 0, "exists": "", "*": "The Lord of the Rings: The Return of the King Photo Guide"}, {"ns": 0, "exists": "", "*": "The Lord of the Rings: The Return of the King Visual Companion"}, {"ns": 0, "exists": "", "*": "The Lord of the Rings: The Third Age"}, {"ns": 0, "exists": "", "*": "The Lord of the Rings: The Two Towers"}, {"ns": 0, "exists": "", "*": "The Lord of the Rings: The Two Towers (extended edition)"}, {"ns": 0, "exists": "", "*": "The Lord of the Rings: The Two Towers (video game)"}, {"ns": 0, "exists": "", "*": "The Lord of the Rings: The Two Towers - Original Motion Picture Soundtrack"}, {"ns": 0, "exists": "", "*": "The Lord of the Rings: The Two Towers - The Complete Recordings"}, {"ns": 0, "exists": "", "*": "The Lord of the Rings: The Two Towers Creatures"}, {"ns": 0, "exists": "", "*": "The Lord of the Rings: The Two Towers Photo Guide"}, {"ns": 0, "exists": "", "*": "The Lord of the Rings: The Two Towers Visual Companion"}, {"ns": 0, "exists": "", "*": "The Lord of the Rings: Weapons and Warfare"}, {"ns": 0, "exists": "", "*": "The Lord of the Rings (film series)"}, {"ns": 0, "exists": "", "*": "The Lord of the Rings Appendices"}, {"ns": 0, "exists": "", "*": "The Lord of the Rings Complete Visual Companion"}, {"ns": 0, "exists": "", "*": "The Lord of the Rings Location Guidebook"}, {"ns": 0, "exists": "", "*": "The Lord of the Rings Location Guidebook: Travel Diary"}, {"ns": 0, "exists": "", "*": "The Lord of the Rings Sketchbook"}, {"ns": 0, "exists": "", "*": "The Lord of the Rings Trilogy Photo Guide"}, {"ns": 0, "exists": "", "*": "The Lost Road and Other Writings"}, {"ns": 0, "exists": "", "*": "The Maps of Middle-earth"}, {"ns": 0, "exists": "", "*": "The Monsters and the Critics, and Other Essays"}, {"ns": 0, "exists": "", "*": "The Music of the Lord of the Rings Films"}, {"ns": 0, "exists": "", "*": "The Nature of Middle-earth"}, {"ns": 0, "exists": "", "*": "The Old English Exodus"}, {"ns": 0, "exists": "", "*": "The Peoples of Middle-earth"}, {"ns": 0, "exists": "", "*": "The Quest of Erebor"}, {"ns": 0, "exists": "", "*": "The Return Journey"}, {"ns": 0, "exists": "", "*": "The Return of the King"}, {"ns": 0, "exists": "", "*": "The Return of the Shadow"}, {"ns": 0, "exists": "", "*": "The Ring of Words"}, {"ns": 0, "exists": "", "*": "The Road Goes Ever On (book)"}, {"ns": 0, "exists": "", "*": "The Road to Middle-earth"}, {"ns": 0, "exists": "", "*": "The Shaping of Middle-earth"}, {"ns": 0, "exists": "", "*": "The Silmarillion"}, {"ns": 0, "exists": "", "*": "The Story of Kullervo"}, {"ns": 0, "exists": "", "*": "The Treason of Isengard"}, {"ns": 0, "exists": "", "*": "The Two Towers"}, {"ns": 0, "exists": "", "*": "The War of the Jewels"}, {"ns": 0, "exists": "", "*": "The War of the Ring"}, {"ns": 0, "exists": "", "*": "There and Back Again: An Actor's Tale"}, {"ns": 0, "exists": "", "*": "There and Back Again (disambiguation)"}, {"ns": 0, "exists": "", "*": "Thorin"}, {"ns": 0, "exists": "", "*": "Thorin Oakenshield"}, {"ns": 0, "exists": "", "*": "Thranduil"}, {"ns": 0, "exists": "", "*": "Thráin"}, {"ns": 0, "exists": "", "*": "Thráin I"}, {"ns": 0, "exists": "", "*": "Thrór"}, {"ns": 0, "exists": "", "*": "Thrór's Map"}, {"ns": 0, "exists": "", "*": "Théoden"}, {"ns": 0, "exists": "", "*": "Tilda"}, {"ns": 0, "exists": "", "*": "Tolkien's Library: An Annotated Checklist"}, {"ns": 0, "exists": "", "*": "Tolkien's Lost Chaucer"}, {"ns": 0, "exists": "", "*": "Tolkien: Maker of Middle-earth"}, {"ns": 0, "exists": "", "*": "Tolkien: Treasures"}, {"ns": 0, "exists": "", "*": "Tolkien On Fairy-stories"}, {"ns": 0, "exists": "", "*": "Tolkien Studies (journal)"}, {"ns": 0, "exists": "", "*": "Tolkien and the Great War"}, {"ns": 0, "exists": "", "*": "Tolkien on Chaucer, 1913-1959"}, {"ns": 0, "exists": "", "*": "Tom"}, {"ns": 0, "exists": "", "*": "Tom Shippey"}, {"ns": 0, "exists": "", "*": "Tree and Leaf"}, {"ns": 0, "exists": "", "*": "Treebeard"}, {"ns": 0, "exists": "", "*": "Trolls"}, {"ns": 0, "exists": "", "*": "Unfinished Tales"}, {"ns": 0, "exists": "", "*": "Vinyar Tengwar"}, {"ns": 0, "exists": "", "*": "W.H. Auden"}, {"ns": 0, "exists": "", "*": "Warg"}, {"ns": 0, "exists": "", "*": "Wayne G. Hammond"}, {"ns": 0, "exists": "", "*": "William"}, {"ns": 0, "exists": "", "*": "William Lawrence Snyder"}, {"ns": 0, "exists": "", "*": "Witch-king"}, {"ns": 0, "exists": "", "*": "Wood-elves"}, {"ns": 0, "exists": "", "*": "Éomer"}, {"ns": 0, "exists": "", "*": "Éowyn"}, {"ns": 0, "exists": "", "*": "Óin"}, {"ns": 2, "exists": "", "*": "User:Luotiansha/3"}, {"ns": 12, "exists": "", "*": "Help:References"}, {"ns": 14, "exists": "", "*": "Category:Images from The Hobbit"}], "templates": [{"ns": 10, "exists": "", "*": "Template:Disambig-more"}, {"ns": 10, "exists": "", "*": "Template:Hatnote"}, {"ns": 10, "exists": "", "*": "Template:Hatnote/styles.css"}, {"ns": 10, "exists": "", "*": "Template:Book"}, {"ns": 10, "exists": "", "*": "Template:Infobox image row"}, {"ns": 10, "exists": "", "*": "Template:Infobox row"}, {"ns": 10, "*": "Template:Usablenext"}, {"ns": 10, "exists": "", "*": "Template:Infobox/styles.css"}, {"ns": 10, "exists": "", "*": "Template:Quote"}, {"ns": 10, "exists": "", "*": "Template:Section divider"}, {"ns": 10, "exists": "", "*": "Template:Section divider/styles.css"}, {"ns": 10, "exists": "", "*": "Template:Quote/styles.css"}, {"ns": 10, "exists": "", "*": "Template:Hchapters"}, {"ns": 10, "exists": "", "*": "Template:Blockquote"}, {"ns": 10, "exists": "", "*": "Template:Fact"}, {"ns": 10, "exists": "", "*": "Template:References"}, {"ns": 10, "exists": "", "*": "Template:L"}, {"ns": 10, "exists": "", "*": "Template:Webcite"}, {"ns": 10, "exists": "", "*": "Template:HH"}, {"ns": 10, "exists": "", "*": "Template:HM"}, {"ns": 10, "exists": "", "*": "Template:IllustratorsHobbit"}, {"ns": 10, "exists": "", "*": "Template:Publishedmajorbooks"}, {"ns": 10, "exists": "", "*": "Template:Hobbitfilms"}, {"ns": 10, "exists": "", "*": "Template:Lordoftheringsfilms"}, {"ns": 10, "exists": "", "*": "Template:Title"}, {"ns": 828, "exists": "", "*": "Module:Paramvalidate"}, {"ns": 828, "exists": "", "*": "Module:Arguments"}], "images": ["The_Hobbit_2016-facsimile.jpeg", "CdxIconArticleDisambiguation.svg", "Donato_Giancola_-_The_Hobbit_-_Expulsion.jpg", "J.R.R._Tolkien_-_Thror's_map.jpg", "J.R.R._Tolkien_-_Bilbo_comes_to_the_Huts_of_the_Raft-elves_(II).jpg", "J.R.R._Tolkien_-_The_Hobbit_Dustcover.png"], "wikitext": {"*": "{{disambig-more|The Hobbit|[[The Hobbit (disambiguation)]]}}\n{{disambig-more|There and Back Again|[[There and Back Again (disambiguation)]]}}\n{{book\n|title=The Hobbit,<br><small>or There and Back Again</small>\n| image = The Hobbit 2016-facsimile.jpeg\n|author=[[J.R.R. Tolkien]]\n|illustrator=J.R.R. Tolkien\n|publisherUK=[[George Allen & Unwin]]\n|publisherUS=[[Houghton Mifflin]]\n|date=[[21 September]] [[1937]]\n|format=Hardcover; paperback; deluxe-edition; audio-book\n|pages=312\n|followedby=[[The Lord of the Rings]] (1954-55)\n|gallery=[[The Hobbit/Publication history and gallery|Publication History and Gallery]]\n}}\n\n{{quote|In a hole in the ground there lived a hobbit.|''The Hobbit'', \"[[An Unexpected Party]]\"}}\n\n'''''The Hobbit, or There and Back Again''''', better known as '''''The Hobbit''''', is a children's fantasy novel by [[J.R.R. Tolkien]]. It was published on [[21 September]] [[1937]] to wide critical acclaim. The book remains popular and is recognised as a classic in children's literature.\n\n''The Hobbit'' is set within Tolkien's [[Middle-earth]] and follows the quest of home-loving [[Bilbo Baggins]], the titular [[hobbit]], to win a share of the treasure guarded by a dragon named [[Smaug]]. Bilbo's journey takes him from his light-hearted, rural surroundings into more sinister territory.\n\nThe story is told in the form of an episodic quest, and most chapters introduce a specific creature or type of creature of Tolkien's geography. Bilbo gains a new level of maturity, competence, and wisdom by accepting the disreputable, romantic, fey, and adventurous sides of his nature and applying his wits and common sense. The story reaches its climax in the [[Battle of Five Armies]], where many of the characters and creatures from earlier chapters re-emerge to engage in conflict.\n\n==Inscription==\nThere is an inscription in the [[Cirth]] characters in the title page, it reads:\n\n:\"''The Hobbit or There and Back Again, being the record of a year's journey made by Bilbo Baggins of Hobbiton; compiled from his memoirs by J.R.R. Tolkien and published by George Allen & Unwin Ltd.''\"<ref name=l12/>\n\n==Synopsis==\n{{hchapters}}\n[[Gandalf]] tricks [[Bilbo Baggins]] into hosting a party for [[Thorin Oakenshield]] and his band of twelve [[dwarves]] ([[Dwalin]], [[Balin]], [[Kíli]], [[Fíli]], [[Dori]], [[Nori]], [[Ori]], [[Óin]], [[Glóin]], [[Bifur]], [[Bofur]], and [[Bombur]]), who sing of reclaiming their ancient home, [[Lonely Mountain]], and its vast treasure from the dragon [[Smaug]]. When the music ends, Gandalf unveils [[Thrór's Map]] showing a [[Back Door|secret door]] into the Mountain and proposes that the dumbfounded Bilbo serve as the expedition's \"burglar\". The dwarves ridicule the idea, but Bilbo, indignant, joins despite himself.\n\nThe group travels into the wild. Gandalf saves the company from [[trolls]] and leads them to [[Rivendell]], where [[Elrond]] reveals more secrets from the map. When they attempt to cross the [[Misty Mountains]], they are caught by [[goblins]] and driven [[Goblin-town|deep underground]]. Although Gandalf rescues them, Bilbo gets separated from the others as they flee the goblins. Lost in the goblin tunnels, he stumbles across [[One Ring|a mysterious ring]] and then encounters [[Gollum]], who engages him in a game, each posing a riddle until one of them cannot solve it. If Bilbo wins, Gollum will show him the way out of the tunnels, but if he fails, his life will be forfeit. With the help of the ring, which confers invisibility, Bilbo escapes and rejoins the dwarves, improving his reputation with them. The goblins and Wargs give chase, but the company are saved by eagles. They rest in the house of [[Beorn]].\n\n[[File:Donato Giancola - The Hobbit - Expulsion.jpg|thumb|left|220px|''Expulsion'' by [[Donato Giancola]]]]\nThe company enters the black forest of [[Mirkwood]] without Gandalf, who has other responsibilities. In Mirkwood, Bilbo first saves the dwarves from giant spiders and then from the dungeons of the [[Wood-elves]]. Nearing the Lonely Mountain, the travellers are welcomed by the human inhabitants of [[Lake-town]], who hope the dwarves will fulfil prophecies of Smaug's demise. The expedition reaches the mountain and finds the secret door. The dwarves send a reluctant Bilbo inside to scout the dragon's lair. He steals a great cup and, while conversing with Smaug, spots a gap in the ancient dragon's armour. The enraged dragon, deducing that Lake-town has aided the intruders, flies off to destroy the town. A thrush overhears Bilbo's report of Smaug's vulnerability and tells Lake-town resident [[Bard]]. Smaug wreaks havoc on the town, until Bard fires an arrow into Smaug's hollow spot, killing the dragon.\n\nWhen the dwarves take possession of the mountain, Bilbo finds the [[Arkenstone]], the most-treasured heirloom of Thorin's family, and hides it away. The Wood-elves and Lake-men request compensation for Lake-town's destruction and settlement of old claims on the treasure. When Thorin refuses to give them anything, they besiege the mountain. However, Thorin manages to send a message to his kinfolk in the [[Iron Hills]] and reinforces his position. Bilbo slips out and gives the Arkenstone to the besiegers, hoping to head off a war. When they offer the jewel to Thorin in exchange for treasure, Bilbo reveals how they obtained it. Thorin, furious at what he sees as betrayal, banishes Bilbo, and battle seems inevitable when [[Dáin Ironfoot]], Thorin's second cousin, arrives with an army of dwarf warriors.\n\nGandalf reappears to warn all of an approaching army of goblins and Wargs. The dwarves, men and elves band together, but only with the timely arrival of the eagles and Beorn do they win the climactic [[Battle of Five Armies]]. Thorin is fatally wounded and reconciles with Bilbo before he dies.\n\nBilbo accepts only a small portion of his share of the treasure, having no want or need for more, but still returns [[Bag End|home]] a very wealthy hobbit roughly a year and a month after he first left. Years later, he [[Red Book of Westmarch|writes the story of his adventures]].\n\n==Characters==\n<div style=\"-moz-column-width: 300px; -webkit-column-width: 300px; column-width: 300px; -moz-column-gap: 15px; -webkit-column-gap: 15px; column-gap: 15px; -webkit-column-rule: 1px solid #cccccc; -moz-column-rule: 1px solid #cccccc; column-rule: 1px solid #cccccc;\">\n# [[Bilbo Baggins]]\n# [[Belladonna Took]] (mentioned only)\n# [[Bungo Baggins]] (mentioned only)\n# [[Gerontius Took|Old Took]] (mentioned only)\n# [[Gandalf|Gandalf the Grey]]\n# [[Thorin|Thorin Oakenshield]]\n# [[Dwalin]]\n# [[Balin]]\n# [[Fíli]]\n# [[Kíli]]\n# [[Óin]]\n# [[Glóin]]\n# [[Dori]]\n# [[Nori]]\n# [[Ori]]\n# [[Bifur]]\n# [[Bofur]]\n# [[Bombur]]\n# [[Smaug]]\n# [[Thráin]] (mentioned only)\n# [[Thrór]] (mentioned only)\n# [[Thráin I]] (mentioned only)\n# [[Azog]] (mentioned only)\n# [[Bandobras Took|Bullroarer Took]] (mentioned only)\n# [[Golfimbul]] (mentioned only)\n# [[William]]\n# [[Tom]]\n# [[Bert]]\n# [[Elrond]]\n# [[Durin]] (mentioned only)\n# [[Great Goblin|The Great Goblin]]\n# [[Gollum]]\n# [[Warg]]s\n# [[Great Eagle|The Lord of the Eagles]]\n# [[Beorn]]\n# [[Radagast|Radagast the Brown]] (mentioned only)\n# [[Thranduil|The Elvenking]] \n# [[Galion]]\n# [[Bard|Bard the Bowman]]\n# [[Master of Lake-town]]\n# [[Girion|Girion of Dale]] (mentioned only)\n# [[Carc]] (mentioned only)\n# [[Roäc]]\n# [[Dáin Ironfoot]]\n# [[Bolg]]\n</div>\n==Illustrations==\n[[File:J.R.R. Tolkien - Thror's map.jpg|thumb|200px|''[[:File:J.R.R. Tolkien - Thror's map.jpg|Thror's map]]'' by J.R.R. Tolkien]]\nAll editions of ''The Hobbit'' contain two maps:\n* ''[[:File:J.R.R. Tolkien - Thror's map.jpg|Thror's map]]''\n* ''[[:File:J.R.R. Tolkien - Map of Wilderland.jpg|Map of Wilderland]]''\n\nMost editions include another series of eight black and white illustrations, in some editions these have been coloured by [[H.E. Riddett]], these are:\n* ''[[:File:J.R.R. Tolkien - The Trolls.png|The Trolls]]''\n* ''[[:File:J.R.R. Tolkien - The Mountain-path.jpg|The Mountain-path]]''\n* ''[[:File:J.R.R. Tolkien - The Misty Mountains looking West from the Eyrie towards Goblin Gate.jpg|The Misty Mountains looking West]]''\n* ''[[:File:J.R.R. Tolkien - Beorn's Hall.jpg|Beorn's Hall]]''\n* ''[[:File:J.R.R. Tolkien - The Elvenking's Gate (II).jpg|The Elvenking's Gate]]''\n* ''[[:File:J.R.R. Tolkien - Lake Town.jpg|Lake Town]]''\n* ''[[:File:J.R.R. Tolkien - The Front Gate.png|The Front Gate]]''\n* ''[[:File:J.R.R. Tolkien - The Hall at Bag-End.jpg|The Hall at Bag-End]]''\n\nTolkien created further new colored illustrations for the American edition by [[Houghton Mifflin]].<ref name=l15 />\n\n==Conception==\n[[File:J.R.R. Tolkien - Bilbo comes to the Huts of the Raft-elves (II).jpg|thumb|200px|''Bilbo comes to the Huts of the Raft-elves'' by J.R.R. Tolkien]]\nTolkien recollects in a 1955 letter to [[W.H. Auden]] (''Letters'', [[Letter 163|no. 163]]) that, in the late 1920s, when he was  Professor of [[Old English|Anglo-Saxon]] at [[Pembroke College]], ''The Hobbit'' began when he was marking School Certificate papers, on the back of one of which he wrote the words \"In a hole in the ground, there lived a hobbit\" which evolved into a story like the ones he was making up for his children. He did not go any further than that at the time, although in the following years he drew up Thrór's map, outlining the geography of the tale. \n\nThe tale itself he wrote in the early 1930s. It was mostly enjoyed by his eldest son [[John Tolkien|John]] (13) than the younger ones. His peers at Oxford also \"forced\" him to lend copies to read.<ref name=l15>{{L|15}}</ref> As early as age four and five, young [[Christopher Tolkien|Christopher]] was concerned with the consistency:\n{{Blockquote|[O]n one occasion I interrupted: 'Last time, you said Bilbo's front door was blue, and you said Thorin had a golden tassel on his hood, but you've just said that Bilbo's front door was green and that Thorin's hood was silver'; at which point my father muttered 'Damn the boy,' and then 'strode across the room' to his desk to make a note.|Christopher Tolkien, foreword to The Hobbit}}\n\nIt was eventually published because he lent it to the Reverend Mother Superior of Cherwell Edge when she was sick with the flu;{{fact}} he had also sent it to his former pupil [[Elaine Griffiths]] who was staying in the Cherwell Edge girl's hostel, and it was seen by her student, Susan Dagnall, who worked in the Allen & Unwin offices. It was the 10-year old son of Sir Stanley Unwin, [[Rayner Unwin]], who wrote such an enthusiastic review of the book that it was published by [[Allen & Unwin]].<ref>{{L|294}}</ref> By [[January]] of [[1937]] Tolkien was corresponding with Allen & Unwin (who also showed interest in ''[[Mr. Bliss]]'' and had to redraw the maps.<ref>{{L|9}}</ref><ref>{{L|10}}</ref> In February he approved the reduction of his illustrations<ref>{{L|11}}</ref> and in April he provided a dust for the dast cover with its runic inscription.<ref name=l12>{{L|12}}</ref>\n\nTolkien introduced or mentioned characters and places that figured prominently in his [[The Book of Lost Tales|personal mythology]], like [[Gondolin]], which added depth, along with elements from Germanic legend.<ref>{{L|257}}</ref> But the decision that the events of ''The Hobbit'' could be part of his [[Legendarium]] was made only after successful publication, when the publisher asked for a sequel. Accordingly, ''The Hobbit'' serves both as an introduction to Middle-Earth and as a link between earlier and later events described in ''The Silmarillion'' and ''The Lord of the Rings'', respectively.\n\nAlthough a fairy tale, the novel is both complex and sophisticated: it contains many names and words derived from Norse mythology, and central plot elements from the ''[[Beowulf (poem)|Beowulf]]'' epic, it makes use of [[Old English|Anglo-Saxon]] [[Runes]], information on calendars and moon phases, and detailed geographical descriptions that fit well with the accompanying maps. Near the end, the tale takes on epic proportions.\n\n==Publication==\n[[File:J.R.R. Tolkien - The Hobbit Dustcover.png|thumb|Dustcover illustration by [[J.R.R. Tolkien]]]]\nGeorge Allen & Unwin, Ltd. of London published the [[The Hobbit 1st edition|first edition of ''The Hobbit'']] on [[21 September]] [[1937]]. It was illustrated with many black-and-white drawings by Tolkien himself. The original printing numbered a mere 1,500 copies and sold out by [[15 December]] that same year due to enthusiastic reviews. Houghton Mifflin of Boston and New York prepared an American edition to be released early in 1938 in which four of the illustrations would be colour plates. Allen & Unwin decided to incorporate the colour illustrations into their second printing, released at the end of 1937.<ref>{{webcite|author=Laura Massey|articleurl=http://www.peterharrington.co.uk/blog/2012/01/identifying-collecting-tolkien-first-editions/|articlename=Identifying & Collecting Tolkien First Editions|dated=9 January 2012|website=[http://www.peterharrington.co.uk/ PeterHarrington.co.uk]|accessed=12 January 2012}}</ref> Despite the book's popularity, wartime conditions forced the London publisher to print small runs of the remaining two printings of the first edition.\n\nAfter its publication, Tolkien's son Christopher was \"hired\" for his eye for consistency and was paid twopence a correction for subsequent publications.<ref>{{L|22}}</ref>\n\nAs remarked above, Tolkien substantially revised ''The Hobbit'''s text describing Bilbo's dealings with Gollum in order to blend the story better into what ''[[The Lord of the Rings]]'' had become. This revision became the second edition, published in 1951 in both UK and American editions.{{fact}} In 1960, Tolkien began a significant [[The 1960 Hobbit|rewrite]] of ''The Hobbit'', intending to reconcile differences in content and style between ''The Hobbit'' and ''The Lord of the Rings'', but abandoned the attempt after only a few chapters.<ref>{{HH|1960}}</ref> Slight corrections to the text have appeared in the third (1966) and fourth editions (1978). (The original version of the Gollum chapter is included in ''[[The Annotated Hobbit]]'', more information about the book's textual changes can be found in ''[[The History of The Hobbit]]''.)\n\nNew [[The Hobbit/Publication history and gallery|English-language editions of ''The Hobbit'']] spring up often, despite the book's age, with [[The Hobbit/Publication history and gallery|at least fifty editions]] having been published to date. Each comes from a different publisher or bears distinctive cover art, internal art, or substantial changes in format. The text of each generally adheres to the Allen & Unwin edition extant at the time it is published.\n\n==Reception==\nOn first publication in October 1937, ''The Hobbit'' was met with almost unanimously favourable reviews from publications both in the UK and the US, including ''[[Wikipedia:The Times|The Times]]'', ''[[Wikipedia:Catholic World|Catholic World]]'', and ''[[Wikipedia:New York Post|New York Post]]''. [[C.S. Lewis]], friend of Tolkien (and later author of ''[[Wikipedia:The Chronicles of Narnia|The Chronicles of Narnia]]'' between 1949 and 1954), writing in ''The Times'' reports:\n\n{{blockquote|The truth is that in this book a number of good things, never before united, have come together: a fund of humour, an understanding of children, and a happy fusion of the scholar's with the poet's grasp of mythology... The professor has the air of inventing nothing. He has studied trolls and dragons at first hand and describes them with that fidelity that is worth oceans of glib 'originality'.}}\n\nLewis compares the book to ''[[Wikipedia:Alice in Wonderland|Alice in Wonderland]]'' in that both children and adults may find different things to enjoy in it, and places it alongside ''[[Wikipedia:Flatland|Flatland]]'', ''[[Wikipedia:Phantastes|Phantastes]]'', and ''[[Wikipedia:The Wind in the Willows|The Wind in the Willows]]''.<ref>Anderson, Douglas A. (ed.). ''[[The Annotated Hobbit]]''</ref> W.H. Auden, in his review of the sequel ''[[The Fellowship of the Ring]]'', calls ''The Hobbit'' \"one of the best children's stories of this century\".<ref>Auden, W.H. [https://www.nytimes.com/books/01/02/11/specials/tolkien-fellowship.html \"The Hero is a Hobbit\"]</ref> Auden was later to correspond with Tolkien, and they became friends.\n\n''The Hobbit'' was nominated for the Carnegie Medal and awarded a prize from the ''New York Herald Tribune'' for best juvenile fiction of the year (1938).<ref>{{HM|A}}Carpenter, Humphrey; Tolkien, Christopher (eds.). ''[[The Letters of J.R.R. Tolkien]]''</ref> More recently, the book has been recognized as \"Most Important 20th-Century Novel (for Older Readers)\" in the ''Children's Books of the Century'' poll in ''Books for Keeps''.<ref>[http://www.tolkiensociety.org/faq01.html#awards \"FAQ: Did Tolkien win any awards for his books?\"]. The Tolkien Society. 2002</ref> In 2012 it was ranked number 14 on a list of the top 100 children's novels published by ''School Library Journal''.<ref>[http://blog.schoollibraryjournal.com/afuse8production/2012/07/07/top-100-chapter-book-poll-results \"Top 100 Chapter Book Poll Results\"]</ref>\n\nPublication of the sequel ''The Lord of the Rings'' altered many critics' reception of the work. Instead of approaching ''The Hobbit'' as a children's book in its own right, critics such as Randel Helms picked up on the idea of ''The Hobbit'' as being a \"prelude\", relegating the story to a dry-run for the later work. Countering a presentist interpretation are those who say this approach misses out on much of the original's value as a children's book and as a work of high fantasy in its own right, and that it disregards the book's influence on these genres.<ref>{{HM|A}}Sullivan, C.W. (1996). ''High Fantasy''</ref> Commentators such as Paul Kocher,<ref>{{HM|A}}Kocher, Paul (1974). ''Master of Middle-earth, the Achievement of J.R.R. Tolkien''</ref> John D. Rateliff,<ref>{{HM|A}}Rateliff, John D. (2007). ''[[The History of The Hobbit]]''</ref> and C.W. Sullivan encourage readers to treat the works separately, both because ''The Hobbit'' was conceived, published, and received independently of the later work, and to avoid dashing readers' expectations of tone and style.\n\n==Adaptations==\n===Radio and audio===\n''The Hobbit'' has been adapted for other media.  [[BBC|BBC Radio 4]] broadcast [[The Hobbit (1968 radio series)|''The Hobbit'' radio drama]], adapted by Michael Kilgarriff, in eight parts (4 hours) from September to November [[1968]], which starred [[Anthony Jackson]] as narrator, [[Paul Daneman]] as Bilbo and [[Heron Carvic]] as Gandalf.\n\n[[Middle-earth]] has been featured in songs notably by [[Enya]] and the [[Brobdingnagian Bards]].  [[Led Zeppelin]]'s songs \"Misty Mountain Hop\" and \"Ramble On\" both contain references to Tolkien's mystical world. For ''The Hobbit'' itself, \"The Ballad of Bilbo Baggins\", performed by [[Leonard Nimoy]] as part of his 1968 ''Two Sides of Leonard Nimoy'' album, is the most pertinent because it recounts the book's storyline in its two minutes.  The ballad's music video became a minor Internet meme in the early 2000s when ''[[The Lord of the Rings (film series)|The Lord of the Rings]]'' movies were released.\n\nIn 1974, Argo Records released an audio adaptation of ''The Hobbit'', with Nicol Williamson providing the voices for all the characters in the book. It was an abridged adaptation, as Williamson re-edited the original script, removing many instances of \"he said\" and so on, preferring instead to rely on his vocal characteristics to convey who was saying what to whom, feeling that this would keep the audience engrossed in the story rather than slowing the overall pace.\n\n===Video games===\nSeveral computer and video games, both official and unofficial, have been based on the story.  One of the first was ''[[The Hobbit (1982 video game)|The Hobbit]]'', a computer game developed in [[1982]] by Beam Software and published by Melbourne House for most computers available at the time, from the more popular computers such as the ZX Spectrum, and the Commodore 64, through to such esoteric computers as the Dragon 32 and Oric computers. By arrangement with publishers, a copy of the novel was included with each game sold.\n\nVivendi Universal Games published ''[[The Hobbit (2003 video game)|The Hobbit: Prelude to The Lord of the Rings]]'' in 2003 for Windows PCs, PlayStation 2, Xbox, and GameCube. It is a hack and slash game produced as a prequel to ''[[The Lord of the Rings]]'' video games, but also as a softer version of those two games: less brutal, fewer enemies but with an important platform aspect, the game was designed for smaller children.  A similar version of this game was also published for the Game Boy Advance.\n\n===Films===\nThe first adaptation of ''The Hobbit'' was presented as ''[[The Hobbit (1967 film)|J.R.R. Tolkien's The Hobbit]]'', and was created by [[Gene Deitch]] in [[1967]]. The film was produced by [[William Lawrence Snyder]] and took less than a month to create. The film was approximately twelve minutes long and was only created so that Snyder could extend his license for ''[[The Lord of the Rings]]'' and sell it back to Tolkien and his publishers, which he did for $100,000.<ref>{{webcite|author=[[Gene Deitch]]|articleurl=http://www.awn.com/articles/profiles/hobbit-alized-first-attempt-animating-hobbit|articlename=Hobbit-alized: The First Attempt At Animating The Hobbit|dated=11 December 2001|website=awn.com|accessed=10 January 2012}}</ref>\n\nAn [[The Hobbit (1977 film)|animated film]] was first broadcasted on [[Sunday]], [[27 November]], [[1977]] on NBC by [[Rankin/Bass]]. It managed to squeeze most of the essential story into its 77 minute runtime and adapts many of Tolkien's songs, making the film a musical.\n\nA [[The Hobbit (film series)|three-part live-action film version of ''The Hobbit'']] based on the book, and incorporating elements from the [[The Lord of the Rings Appendices|Apprendices]] of ''[[The Lord of the Rings]]'' was produced and directed by [[Peter Jackson]], who had also produced and directed [[The Lord of the Rings (film series)|a film adaptation of ''The Lord of the Rings'']]. Principal photography began in 2011 and ended in 2012, with the majority of the scenes being shot in [[New Zealand]].\n\nThis film series was released in three parts: ''[[The Hobbit: An Unexpected Journey]]'' was released on 14 December 2012; ''[[The Hobbit: The Desolation of Smaug]]'' was released on 13 December 2013; and ''[[The Hobbit: The Battle of the Five Armies]]'' was released worldwide on 17 December 2014.\n\n===Miscellaneous===\nA [[:File:The Hobbit (dramatised by Patricia Gray).png|drama playscript]] was published in [[1968]], which is made of multiple simple sets and runs about 2 hours. A [[The Hobbit (1985 television film)|live action television dramatisation]] was broadcast on USSR televsion in [[1985]]. [[David T. Wenzel]]'s [[The Hobbit (comic book)|graphic format adaptation]] of ''The Hobbit'' was published in [[1989]].\n\n==Publication history and gallery==\n:''Please see [[The Hobbit/Publication history and gallery|Publication history and gallery]].''\n\n==See also==\n*[[Poems in The Hobbit|Poems in ''The Hobbit'']]\n*[[The Hobbit/Translations|Translations of ''The Hobbit'']]\n*\"[[The Quest of Erebor]]\", from ''[[Unfinished Tales]]'' \n*[[:Category:Images from The Hobbit|Images from ''The Hobbit'']] illustrated by [[Alan Lee]]\n\n;Related books\n*''[[The Annotated Hobbit]]'' by [[Douglas A. Anderson]]\n*''[[The History of The Hobbit]]'' by [[John D. Rateliff]]\n*''[[The Art of The Hobbit]]'' by [[Wayne G. Hammond]] and [[Christina Scull]]\n*''[[Poems from The Hobbit]]''\n\n==External links==\n* [http://www.hobbit.ca/Library.html Collection of edition covers, 1937&ndash;2005]\n* [http://www.tolkienbooks.net/html/the_hobbit.htm UK editions of ''The Hobbit'']\n*[http://www.telegraph.co.uk/culture/books/booknews/9555838/The-Hobbit-What-has-made-the-book-such-an-enduring-success.html ''The Hobbit'': What has made the book such an enduring success?] by [[Tom Shippey]]\n* [http://www.tolkienlibrary.com/reviews/dutch-de_hobbit.htm Every Dutch edition of ''The Hobbit'']\n* [http://www.tolkienlibrary.com/translations/hobbits/index.htm ''Hobbits'' around the globe - gallery]\n\n{{References}}\n{{IllustratorsHobbit}}\n{{Publishedmajorbooks}}\n{{hobbitfilms}}\n{{lordoftheringsfilms}}\n{{title|italics}}\n{{DEFAULTSORT:Hobbit}}\n[[Category:Books by J.R.R. Tolkien]]\n[[Category:Fiction books]]\n[[Category:The Hobbit| ]]\n[[Category:Publications by title]]\n\n[[de:Der Hobbit]]\n[[fi:Hobitti eli Sinne ja takaisin]]\n[[fr:tolkien/biblio/bh]]"}}}