{"parse": {"title": "LEP", "pageid": 34539, "redirects": [], "links": [{"ns": 0, "exists": "", "*": "1915"}, {"ns": 0, "exists": "", "*": "1917"}, {"ns": 0, "exists": "", "*": "1937"}, {"ns": 0, "exists": "", "*": "Arden R. Smith"}, {"ns": 0, "exists": "", "*": "Carl F. Hostetter"}, {"ns": 0, "exists": "", "*": "Christopher Gilson"}, {"ns": 0, "exists": "", "*": "Christopher Tolkien"}, {"ns": 0, "exists": "", "*": "Common Eldarin"}, {"ns": 0, "exists": "", "*": "Elf (Gnomish)"}, {"ns": 0, "exists": "", "*": "Gnomish"}, {"ns": 0, "exists": "", "*": "J.R.R. Tolkien"}, {"ns": 0, "exists": "", "*": "Leben"}, {"ns": 0, "exists": "", "*": "Lemin"}, {"ns": 0, "exists": "", "*": "Lempe"}, {"ns": 0, "exists": "", "*": "Lepen"}, {"ns": 0, "exists": "", "*": "Lheben"}, {"ns": 0, "exists": "", "*": "Noldorin"}, {"ns": 0, "exists": "", "*": "Parma Eldalamberon 11"}, {"ns": 0, "exists": "", "*": "Parma Eldalamberon 12"}, {"ns": 0, "exists": "", "*": "Parma Eldalamberon 17"}, {"ns": 0, "exists": "", "*": "Patrick H. Wynne"}, {"ns": 0, "exists": "", "*": "Qenya"}, {"ns": 0, "exists": "", "*": "Quenya"}, {"ns": 0, "exists": "", "*": "Sindarin"}, {"ns": 0, "exists": "", "*": "Sundocarme"}, {"ns": 0, "exists": "", "*": "Telerin"}, {"ns": 0, "exists": "", "*": "The Etymologies"}, {"ns": 0, "exists": "", "*": "The Lost Road and Other Writings"}, {"ns": 0, "exists": "", "*": "The Rivers and Beacon-hills of Gondor"}, {"ns": 0, "exists": "", "*": "Vinyar Tengwar 42"}, {"ns": 0, "exists": "", "*": "Vinyar Tengwar 45"}, {"ns": 0, "exists": "", "*": "Vinyar Tengwar 47"}, {"ns": 0, "exists": "", "*": "Vinyar Tengwar 48"}], "templates": [{"ns": 10, "exists": "", "*": "Template:References"}, {"ns": 10, "exists": "", "*": "Template:VT"}, {"ns": 10, "exists": "", "*": "Template:PE"}, {"ns": 10, "exists": "", "*": "Template:LR"}], "images": [], "wikitext": {"*": "'''LEP''' is a [[Common Eldarin]]<!-- We usually write \"Primitive Quendian\", but since the source spec. says \"Common Eldarin\", I've used that (User:Morgan) --> [[Sundocarme|root]] signifying \"finger\",<ref name=VT42>{{VT|42b}}, pp. 24-26</ref> or \"pick (up, out) with the fingers\".<ref name=VT47>{{VT|47a}}, p. 24</ref>\n\n==Derivatives==\n\n*[[Common Eldarin]]: ''leper-''<ref name=VT47/>\n**[[Quenya]]: ''lepta-'' (\"finger, feel with fingertips\"); ''leper''<ref name=VT47/>\n**[[Telerin]]: ''lepta-'' (\"finger, feel with fingertips\"); ''leper''<ref name=VT47/>\n**[[Sindarin]]: ''leber''<ref name=VT47/>\n\n*Quenya: ''[[lempe]]''<ref name=VT42/><ref name=VT47/>\n*Telerin ''[[lepen]]''<ref name=VT42/><ref name=VT47/>\n*Sindarin ''[[leben]]''<ref name=VT42/><ref name=VT47/>\n\n==Other versions==\n\nIn the manuscript \"Words, Phrases and Passages in ''The Lord of the Rings''\" (late 1950, early 1960s) appears the root LEPEN (or LENEP), yielding the derivatives Quenya ''[[lempe]]'' and Sindarin ''[[leben]]''.<ref>{{PE|17}}, pp. 95-6, 160 (roots appearing as \"√LEPEN or LENEP\")</ref>\n\nIn the ''[[The Etymologies|Etymologies]]'' (ca. [[1937]]) appears the root LEP-, LEPET signifying \"finger\", yielding the derivatives Quenya ''lepse'', [[Noldorin]] ''lhebed''. The extended forms LEPEN, LEPEK, signifying \"five\", yield Quenya ''[[lempe]]'', Quenya ''lemnar'' (\"week\"), and Noldorin ''[[lheben]]'', Noldorin ''lhevnar'' (\"week\").<ref>{{LR|Etymologies}}, p. 368</ref><ref>{{VT|45a}}, p. 27</ref><ref name=VT48/>\n\nIn the ''Gnomish Lexicon'' (ca. [[1917]]) appears the root ''lef-'', yielding the derivatives [[Qenya]] ''[[lemin|lempe]]'' and [[Gnomish]] ''[[Elf (Gnomish)|elf]]''.<ref name=VT48>{{VT|48a}}, p. 20 (note 17)</ref><ref name=PE11>{{PE|11}}, p. 53 (root appearing as (\"√''lef-''\")</ref>\n\nIn the ''Qenya Lexicon'' (ca. [[1915]]) appears the root LEPE, with the derivative [[Qenya]] ''let'' (\"finger\").<ref>{{PE|12}}</ref>\n\n{{references}}\n\n[[Category:Roots]]"}}}