{"parse": {"title": "Arador", "pageid": 1230, "redirects": [], "links": [{"ns": 14, "exists": "", "*": "Category:Images of Arador"}, {"ns": 6, "exists": "", "*": "File:Born of Hope - Arador.jpg"}, {"ns": 0, "exists": "", "*": "Amlaith"}, {"ns": 0, "exists": "", "*": "Appendix A"}, {"ns": 0, "exists": "", "*": "Ara"}, {"ns": 0, "exists": "", "*": "Araglas"}, {"ns": 0, "exists": "", "*": "Aragorn"}, {"ns": 0, "exists": "", "*": "Aragorn I"}, {"ns": 0, "exists": "", "*": "Aragorn II"}, {"ns": 0, "exists": "", "*": "Aragost"}, {"ns": 0, "exists": "", "*": "Arahad I"}, {"ns": 0, "exists": "", "*": "Arahad II"}, {"ns": 0, "exists": "", "*": "Arahael"}, {"ns": 0, "exists": "", "*": "Aranarth"}, {"ns": 0, "exists": "", "*": "Arantar"}, {"ns": 0, "exists": "", "*": "Aranuir"}, {"ns": 0, "exists": "", "*": "Araphant"}, {"ns": 0, "exists": "", "*": "Araphor"}, {"ns": 0, "exists": "", "*": "Arassuil"}, {"ns": 0, "exists": "", "*": "Arathorn I"}, {"ns": 0, "exists": "", "*": "Arathorn II"}, {"ns": 0, "exists": "", "*": "Araval"}, {"ns": 0, "exists": "", "*": "Aravir"}, {"ns": 0, "exists": "", "*": "Aravorn"}, {"ns": 0, "exists": "", "*": "Argeleb I"}, {"ns": 0, "exists": "", "*": "Argeleb II"}, {"ns": 0, "exists": "", "*": "Argonui"}, {"ns": 0, "exists": "", "*": "Arnor"}, {"ns": 0, "exists": "", "*": "Arvedui"}, {"ns": 0, "exists": "", "*": "Arvegil"}, {"ns": 0, "exists": "", "*": "Arveleg I"}, {"ns": 0, "exists": "", "*": "Arveleg II"}, {"ns": 0, "exists": "", "*": "Beleg (King of Arthedain)"}, {"ns": 0, "exists": "", "*": "Born of Hope"}, {"ns": 0, "exists": "", "*": "Carl F. Hostetter"}, {"ns": 0, "exists": "", "*": "Celebrindor"}, {"ns": 0, "exists": "", "*": "Celepharn"}, {"ns": 0, "exists": "", "*": "Chieftain of the Dúnedain"}, {"ns": 0, "exists": "", "*": "Chieftains of the Dúnedain"}, {"ns": 0, "exists": "", "*": "Christopher Tolkien"}, {"ns": 0, "exists": "", "*": "Coldfells"}, {"ns": 0, "exists": "", "*": "Dírhael"}, {"ns": 0, "exists": "", "*": "Dúnedain of the North"}, {"ns": 0, "exists": "", "*": "Eldacar (King of Arnor)"}, {"ns": 0, "exists": "", "*": "Eldarion"}, {"ns": 0, "exists": "", "*": "Elendil"}, {"ns": 0, "exists": "", "*": "Elendur (King of Arnor)"}, {"ns": 0, "exists": "", "*": "Eärendur (King of Arnor)"}, {"ns": 0, "exists": "", "*": "Fourth Age"}, {"ns": 0, "exists": "", "*": "Fourth Age 120"}, {"ns": 0, "exists": "", "*": "Gilbarad"}, {"ns": 0, "exists": "", "*": "Gilraen"}, {"ns": 0, "exists": "", "*": "Heir of Isildur"}, {"ns": 0, "exists": "", "*": "Hill-trolls"}, {"ns": 0, "exists": "", "*": "Hoarwell"}, {"ns": 0, "exists": "", "*": "House of Elros"}, {"ns": 0, "exists": "", "*": "House of Isildur"}, {"ns": 0, "exists": "", "*": "Isildur"}, {"ns": 0, "exists": "", "*": "Ivorwen"}, {"ns": 0, "exists": "", "*": "J.R.R. Tolkien"}, {"ns": 0, "exists": "", "*": "Kings of Arnor"}, {"ns": 0, "exists": "", "*": "Kings of Arthedain"}, {"ns": 0, "exists": "", "*": "Lenition"}, {"ns": 0, "exists": "", "*": "Loudwater"}, {"ns": 0, "exists": "", "*": "Mallor"}, {"ns": 0, "exists": "", "*": "Malvegil"}, {"ns": 0, "exists": "", "*": "Rivendell"}, {"ns": 0, "exists": "", "*": "Second Age"}, {"ns": 0, "exists": "", "*": "Second Age 3320"}, {"ns": 0, "exists": "", "*": "Second Age 3441"}, {"ns": 0, "exists": "", "*": "Sindarin"}, {"ns": 0, "exists": "", "*": "Tarcil"}, {"ns": 0, "exists": "", "*": "Tarondor (King of Arnor)"}, {"ns": 0, "exists": "", "*": "The Heirs of Elendil"}, {"ns": 0, "exists": "", "*": "The Lord of the Rings"}, {"ns": 0, "exists": "", "*": "The Lord of the Rings Online"}, {"ns": 0, "exists": "", "*": "The Nature of Middle-earth"}, {"ns": 0, "exists": "", "*": "The Peoples of Middle-earth"}, {"ns": 0, "exists": "", "*": "The Tale of Aragorn and Arwen"}, {"ns": 0, "exists": "", "*": "Third Age"}, {"ns": 0, "exists": "", "*": "Third Age 1029"}, {"ns": 0, "exists": "", "*": "Third Age 1110"}, {"ns": 0, "exists": "", "*": "Third Age 1191"}, {"ns": 0, "exists": "", "*": "Third Age 1272"}, {"ns": 0, "exists": "", "*": "Third Age 1349"}, {"ns": 0, "exists": "", "*": "Third Age 1356"}, {"ns": 0, "exists": "", "*": "Third Age 1409"}, {"ns": 0, "exists": "", "*": "Third Age 1589"}, {"ns": 0, "exists": "", "*": "Third Age 1670"}, {"ns": 0, "exists": "", "*": "Third Age 1743"}, {"ns": 0, "exists": "", "*": "Third Age 1813"}, {"ns": 0, "exists": "", "*": "Third Age 1891"}, {"ns": 0, "exists": "", "*": "Third Age 1964"}, {"ns": 0, "exists": "", "*": "Third Age 1975"}, {"ns": 0, "exists": "", "*": "Third Age 2"}, {"ns": 0, "exists": "", "*": "Third Age 2106"}, {"ns": 0, "exists": "", "*": "Third Age 2177"}, {"ns": 0, "exists": "", "*": "Third Age 2247"}, {"ns": 0, "exists": "", "*": "Third Age 2319"}, {"ns": 0, "exists": "", "*": "Third Age 2327"}, {"ns": 0, "exists": "", "*": "Third Age 2455"}, {"ns": 0, "exists": "", "*": "Third Age 249"}, {"ns": 0, "exists": "", "*": "Third Age 2523"}, {"ns": 0, "exists": "", "*": "Third Age 2588"}, {"ns": 0, "exists": "", "*": "Third Age 2654"}, {"ns": 0, "exists": "", "*": "Third Age 2693"}, {"ns": 0, "exists": "", "*": "Third Age 2719"}, {"ns": 0, "exists": "", "*": "Third Age 2757"}, {"ns": 0, "exists": "", "*": "Third Age 2784"}, {"ns": 0, "exists": "", "*": "Third Age 2820"}, {"ns": 0, "exists": "", "*": "Third Age 2848"}, {"ns": 0, "exists": "", "*": "Third Age 2873"}, {"ns": 0, "exists": "", "*": "Third Age 2907"}, {"ns": 0, "exists": "", "*": "Third Age 2912"}, {"ns": 0, "exists": "", "*": "Third Age 2930"}, {"ns": 0, "exists": "", "*": "Third Age 2931"}, {"ns": 0, "exists": "", "*": "Third Age 2933"}, {"ns": 0, "exists": "", "*": "Third Age 3007"}, {"ns": 0, "exists": "", "*": "Third Age 3019"}, {"ns": 0, "exists": "", "*": "Third Age 339"}, {"ns": 0, "exists": "", "*": "Third Age 435"}, {"ns": 0, "exists": "", "*": "Third Age 515"}, {"ns": 0, "exists": "", "*": "Third Age 602"}, {"ns": 0, "exists": "", "*": "Third Age 652"}, {"ns": 0, "exists": "", "*": "Third Age 777"}, {"ns": 0, "exists": "", "*": "Third Age 861"}, {"ns": 0, "exists": "", "*": "Third Age 946"}, {"ns": 0, "exists": "", "*": "Trolls"}, {"ns": 0, "exists": "", "*": "Trollshaws"}, {"ns": 0, "exists": "", "*": "Valandil (King of Arnor)"}, {"ns": 0, "exists": "", "*": "Valandur"}, {"ns": 0, "exists": "", "*": "Westron"}], "templates": [{"ns": 10, "exists": "", "*": "Template:Infobox character"}, {"ns": 10, "exists": "", "*": "Template:Infobox image row"}, {"ns": 10, "exists": "", "*": "Template:Infobox row"}, {"ns": 10, "exists": "", "*": "Template:TA"}, {"ns": 10, "exists": "", "*": "Template:Infobox ribbon row"}, {"ns": 10, "exists": "", "*": "Template:Infobox ribbon row/styles.css"}, {"ns": 10, "exists": "", "*": "Template:Infobox/styles.css"}, {"ns": 10, "exists": "", "*": "Template:IPA"}, {"ns": 10, "exists": "", "*": "Template:Familytree/start"}, {"ns": 10, "exists": "", "*": "Template:Familytree"}, {"ns": 10, "exists": "", "*": "Template:Familytree/step2"}, {"ns": 10, "exists": "", "*": "Template:Familytree/styles.css"}, {"ns": 10, "exists": "", "*": "Template:FoA"}, {"ns": 10, "exists": "", "*": "Template:Familytree/end"}, {"ns": 10, "exists": "", "*": "Template:References"}, {"ns": 10, "exists": "", "*": "Template:PM"}, {"ns": 10, "exists": "", "*": "Template:App"}, {"ns": 10, "exists": "", "*": "Template:NM"}, {"ns": 10, "exists": "", "*": "Template:Webcite"}, {"ns": 10, "exists": "", "*": "Template:Seq-start"}, {"ns": 10, "exists": "", "*": "Template:Seq-head"}, {"ns": 10, "exists": "", "*": "Template:Seq"}, {"ns": 10, "exists": "", "*": "Template:Seq-end"}, {"ns": 10, "exists": "", "*": "Template:Seq/styles.css"}, {"ns": 10, "exists": "", "*": "Template:Northernline"}, {"ns": 10, "exists": "", "*": "Template:SA"}, {"ns": 828, "exists": "", "*": "Module:Paramvalidate"}, {"ns": 828, "exists": "", "*": "Module:Arguments"}], "images": ["Born_of_Hope_-_Arador.jpg", "The_Lord_of_the_Rings_Online_-_Arador.jpg"], "wikitext": {"*": "{{infobox character\n| people=[[Arnor]]ian\n| name=Arador\n| image=Born of Hope - Arador.jpg\n| caption=Arador from ''[[Born of Hope]]''\n| pronun=\n| othernames=\n| titles=[[Chieftain of the Dúnedain]]\n| position=\n| location=[[Rivendell]]\n| affiliation=\n| language=[[Sindarin]], [[Westron]]\n| birth={{TA|2820}}\n| birthlocation=\n| rule={{TA|2912}} - {{TA|2930|n}}\n| death={{TA|2930}}\n| deathlocation=[[Coldfells]]\n| age=110\n| notablefor=\n| house=[[House of Isildur]]\n| parentage=[[Argonui]]\n| siblings=\n| spouse=\n| children=[[Arathorn II]]\n| gender=Male\n| height=\n| hair=\n| eyes=\n| clothing=\n| weapons=\n| steed=\n}}\n'''Arador''' ([[Sindarin|S]], pron. {{IPA|[ˈarador]}}; {{TA|2820}}<ref>{{PM|Elendil}}, manuscript C, The Chieftains of the Dúnedan, 14. Arador, p. 196</ref> - {{TA|2930|n}},<ref>{{App|North}}, ''Chieftains'', entry for Arador, p. 1038</ref> died aged 110) was the fourteenth [[Chieftain of the Dúnedain]].\n\n==History==\nArador succeeded his father, [[Argonui]], when he died in {{TA|2912|n}}.<ref>{{App|North}}, ''Chieftains'', entry for Argonui, p. 1038</ref>\n\nIn his time many [[Dúnedain of the North]] lived in woods between the river [[Hoarwell]] and the river [[Loudwater]]. Arador lived in a house north of the  [[Trollshaws]] in woods near the river [[Hoarwell]], which was threatened by a group of [[Trolls]].<ref>{{NM|P3xvii}}, note 12, p. 366</ref>\n\nHis rule was uneventful except for the fact that he was captured by [[Hill-trolls]] in the [[Coldfells]] north of [[Rivendell]] and killed by them.<ref>{{App|Tale}}, p. 1057</ref> He was succeeded by his young son, [[Arathorn II]], in {{TA|2930|n}}.<ref>{{App|North}}, ''Chieftains'', entry for Arathorn II, p. 1038</ref>\n\n==Etymology==\n''Arador'' is a [[Sindarin]] name. Its meaning is not glossed, but Paul Strack suggests it means \"Noble-lord\" and is a compound of the prefix ''[[ara|ar(a)-]]'' (\"noble\", \"royal\", \"high\") and the [[lenition|lenited]] form ''-dor'' of ''taur'' (\"lord\").<ref>{{webcite|author=Paul Strack|articleurl=https://www.eldamo.org/content/words/word-2275977149.html|articlename=S. ''Arador'' m.|website=Eldamo|accessed=05 February 2022}}</ref> The Association Tolkiendil suggests it means \"Royal Lord\".<ref>{{webcite|author=Assocation  Tolkiendil|articleurl=https://www.tolkiendil.com/langues/english/i-lam_arth/compound_sindarin_names|articlename=Compound Sindarin Names in Middle-earth|website=Tolkiendil|accessed=05 February 2022}}</ref>\n\n== Genealogy ==\n{{familytree/start}}\n{{familytree | | | HOS | | | | | | |HOS=''[[House of Isildur]]''}}\n{{familytree | | | |:| | | | | | | |}}\n{{familytree | | | |:| | | | | | | |}}\n{{familytree | | | ARA | | | | HOU |ARA=[[Arathorn I]]<br/><small>''{{TA|2693|n}} - {{TA|2848|n}}''†</small>|HOU=''[[House of Isildur]]''}}\n{{familytree | |,|-|^|-|.| | | |:| |}}\n{{familytree | ARG | | UNK | | GIL |ARG=[[Argonui]]<br/><small>''{{TA|2757|n}} - {{TA|2912|n}}''</small>|GIL=[[Gilbarad]]<br/><small>''b. {{TA}}''</small>|UNK=''unknown<br />child''<sup>[[Arathorn I#Other versions of the legendarium|NB]]</sup>}}\n{{familytree | |!| | | |:| | | |!| |}}\n{{familytree | ARA | | DIR |y| IVO |ARA='''ARADOR'''<br/><small>''{{TA|2820|n}} - {{TA|2930|n}}''†</small>|DIR=[[Dírhael]]<br/><small>''b. {{TA}}''</small>|IVO=[[Ivorwen]]<br/><small>''b. {{TA}}''</small>}}\n{{familytree | |!| | | | | |!| | | |}}\n{{familytree | ATH |~|y|~| GIR | | |ATH=[[Arathorn II]]<br/><small>''{{TA|2873|n}} - {{TA|2933|n}}''†</small>|GIR=[[Gilraen]]<br/><small>''{{TA|2907|n}} - {{TA|3007|n}}''</small>}}\n{{familytree | | | | |!| | | | | | |}}\n{{familytree | | | | ELE | | | | | |ELE=[[Aragorn II]] '''Elessar'''<br/><small>''{{TA|2931}} - {{FoA|120}}''</small>}}\n{{familytree/end}}\n\n==Portrayal in adaptations==\n[[File:The Lord of the Rings Online - Arador.jpg|thumb|Arador's body in ''[[The Lord of the Rings Online]]'']]\n'''2010: ''[[The Lord of the Rings Online]]'':'''\n:Arador's death is shown in a Session Play narrating the history of the House of Isildur.\n\n{{references}}\n{{seq-start}}\n{{seq-head\n| race=arnorian\n| house=[[House of Isildur]]<small><br/>Cadet branch of [[House of Elros]]</small>\n| born={{TA|2820}}\n| died={{TA|2930}}\n}}\n{{seq\n| prow=2\n| prev=[[Argonui]]\n| list=37th [[Heir of Isildur|Heir]] of [[Isildur]]\n| dates={{TA|2912}} - {{TA|2930}}\n| next=[[Arathorn II]]\n| nrow=2\n}}\n{{seq\n| list=14th [[Chieftains of the Dúnedain|Chieftain of the Dúnedain]]\n| dates={{TA|2912}} - {{TA|2930}}\n}}\n{{seq-end}}\n\n{{northernline}}\n[[Category:Chieftains of the Dúnedain]]\n[[Category:House of Isildur]]\n[[Category:Sindarin names]]\n[[Category:Third Age characters]]\n[[de:Arador]]\n[[fi:Arador]]\n[[fr:encyclo/personnages/hommes/3a/dunedain/dunedain du nord/arador]]"}}}