{"parse": {"title": "Helm's Deep (soundtrack)", "pageid": 46032, "redirects": [], "links": [{"ns": 6, "exists": "", "*": "File:The Lord of the Rings - The Two Towers - Original Motion Picture Soundtrack.jpg"}, {"ns": 0, "exists": "", "*": "Helm's Deep (disambiguation)"}, {"ns": 0, "exists": "", "*": "Howard Shore"}, {"ns": 0, "exists": "", "*": "The Forbidden Pool (soundtrack)"}, {"ns": 0, "exists": "", "*": "The Leave Taking"}, {"ns": 0, "exists": "", "*": "The Lord of the Rings: The Two Towers - Original Motion Picture Soundtrack"}], "templates": [{"ns": 10, "exists": "", "*": "Template:Title"}, {"ns": 10, "exists": "", "*": "Template:Disambig-more"}, {"ns": 10, "exists": "", "*": "Template:Hatnote"}, {"ns": 10, "exists": "", "*": "Template:Hatnote/styles.css"}, {"ns": 10, "exists": "", "*": "Template:Song"}, {"ns": 10, "exists": "", "*": "Template:Infobox image row"}, {"ns": 10, "exists": "", "*": "Template:Infobox row"}, {"ns": 10, "exists": "", "*": "Template:Infobox/styles.css"}, {"ns": 828, "exists": "", "*": "Module:Paramvalidate"}, {"ns": 828, "exists": "", "*": "Module:Arguments"}], "images": ["The_Lord_of_the_Rings_-_The_Two_Towers_-_Original_Motion_Picture_Soundtrack.jpg", "CdxIconArticleDisambiguation.svg"], "wikitext": {"*": "{{title}}\n{{disambig-more|Helm's Deep|[[Helm's Deep (disambiguation)]]}}\n{{song\n| title = Helm's Deep\n| image = The Lord of the Rings - The Two Towers - Original Motion Picture Soundtrack.jpg\n| album = [[The Lord of the Rings: The Two Towers - Original Motion Picture Soundtrack]]\n| composer = [[Howard Shore]]\n| performer = [[Wikipedia:London Philharmonic Orchestra|London Philharmonic Orchestra]]\n| duration = 3:53\n| track = 12\n| previous = [[The Leave Taking]]\n| next = [[The Forbidden Pool (soundtrack)|The Forbidden Pool]]\n| spotify = https://open.spotify.com/track/7wXJbYOY984zsuQFgOV0OK\n}}\n'''Helm's Deep''' is the twelfth track of ''[[The Lord of the Rings: The Two Towers - Original Motion Picture Soundtrack]]'' by [[Howard Shore]]. \n\n[[Category:The Lord of the Rings: The Two Towers - Original Motion Picture Soundtrack|12]]"}}}