{"parse": {"title": "Timeline", "pageid": 952, "redirects": [], "links": [{"ns": 0, "exists": "", "*": "14 October"}, {"ns": 0, "exists": "", "*": "1958"}, {"ns": 0, "exists": "", "*": "Aman"}, {"ns": 0, "exists": "", "*": "Anduin"}, {"ns": 0, "exists": "", "*": "Angmar War"}, {"ns": 0, "exists": "", "*": "Aragorn"}, {"ns": 0, "exists": "", "*": "Arda"}, {"ns": 0, "exists": "", "*": "Arda Marred"}, {"ns": 0, "exists": "", "*": "Arnor"}, {"ns": 0, "exists": "", "*": "Aulë"}, {"ns": 0, "exists": "", "*": "Awakening of Men"}, {"ns": 0, "exists": "", "*": "Awakening of the Elves"}, {"ns": 0, "exists": "", "*": "Battle of the Powers"}, {"ns": 0, "exists": "", "*": "Battles of Beleriand"}, {"ns": 0, "exists": "", "*": "Carl F. Hostetter"}, {"ns": 0, "exists": "", "*": "Chaining of Melkor"}, {"ns": 0, "exists": "", "*": "Changing of the World"}, {"ns": 0, "exists": "", "*": "Christopher Tolkien"}, {"ns": 0, "exists": "", "*": "Cuiviénen"}, {"ns": 0, "exists": "", "*": "Dagor Dagorath"}, {"ns": 0, "exists": "", "*": "Darkening of Valinor"}, {"ns": 0, "exists": "", "*": "Days before days"}, {"ns": 0, "exists": "", "*": "Dominion of Men"}, {"ns": 0, "exists": "", "*": "Downfall of Númenor"}, {"ns": 0, "exists": "", "*": "Durin's Folk"}, {"ns": 0, "exists": "", "*": "Durin VII"}, {"ns": 0, "exists": "", "*": "Dwarves"}, {"ns": 0, "exists": "", "*": "Dúnedain"}, {"ns": 0, "exists": "", "*": "Eagles"}, {"ns": 0, "exists": "", "*": "Eldar"}, {"ns": 0, "exists": "", "*": "Eldarion"}, {"ns": 0, "exists": "", "*": "Elenna"}, {"ns": 0, "exists": "", "*": "Elves"}, {"ns": 0, "exists": "", "*": "Ents"}, {"ns": 0, "exists": "", "*": "Fathers of the Dwarves"}, {"ns": 0, "exists": "", "*": "First Age"}, {"ns": 0, "exists": "", "*": "First War"}, {"ns": 0, "exists": "", "*": "Fourth Age"}, {"ns": 0, "exists": "", "*": "Fourth Age 120"}, {"ns": 0, "exists": "", "*": "Fëanor"}, {"ns": 0, "exists": "", "*": "Gondor"}, {"ns": 0, "exists": "", "*": "Great Journey"}, {"ns": 0, "exists": "", "*": "Hildórien"}, {"ns": 0, "exists": "", "*": "History of Arda"}, {"ns": 0, "exists": "", "*": "House of Anárion"}, {"ns": 0, "exists": "", "*": "Humphrey Carpenter"}, {"ns": 0, "exists": "", "*": "Iron Mountains"}, {"ns": 0, "exists": "", "*": "J.R.R. Tolkien"}, {"ns": 0, "exists": "", "*": "Last Ship"}, {"ns": 0, "exists": "", "*": "Later Ages"}, {"ns": 0, "exists": "", "*": "Letter 211"}, {"ns": 0, "exists": "", "*": "Maiar"}, {"ns": 0, "exists": "", "*": "Manwë"}, {"ns": 0, "exists": "", "*": "Men"}, {"ns": 0, "exists": "", "*": "Middle-earth"}, {"ns": 0, "exists": "", "*": "Morgoth"}, {"ns": 0, "exists": "", "*": "Moria"}, {"ns": 0, "exists": "", "*": "Music of the Ainur"}, {"ns": 0, "exists": "", "*": "Nazgûl"}, {"ns": 0, "exists": "", "*": "Númenor"}, {"ns": 0, "exists": "", "*": "Reunited Kingdom"}, {"ns": 0, "exists": "", "*": "Rings of Power"}, {"ns": 0, "exists": "", "*": "Sauron"}, {"ns": 0, "exists": "", "*": "Second Age"}, {"ns": 0, "exists": "", "*": "Second Music of the Ainur"}, {"ns": 0, "exists": "", "*": "Silmarils"}, {"ns": 0, "exists": "", "*": "Spring of Arda"}, {"ns": 0, "exists": "", "*": "Stars"}, {"ns": 0, "exists": "", "*": "Thain's Book"}, {"ns": 0, "exists": "", "*": "The Letters of J.R.R. Tolkien"}, {"ns": 0, "exists": "", "*": "The Nature of Middle-earth"}, {"ns": 0, "exists": "", "*": "The One Ring"}, {"ns": 0, "exists": "", "*": "The Peoples of Middle-earth"}, {"ns": 0, "exists": "", "*": "The Tale of Years of the Third Age"}, {"ns": 0, "exists": "", "*": "Third Age"}, {"ns": 0, "exists": "", "*": "Three Rings"}, {"ns": 0, "exists": "", "*": "Timeline/Days before days"}, {"ns": 0, "exists": "", "*": "Timeline/First Age"}, {"ns": 0, "exists": "", "*": "Timeline/Fourth Age"}, {"ns": 0, "exists": "", "*": "Timeline/Second Age"}, {"ns": 0, "exists": "", "*": "Timeline/Third Age"}, {"ns": 0, "exists": "", "*": "Timeline/Years of the Trees"}, {"ns": 0, "exists": "", "*": "Timeline of Aragorn"}, {"ns": 0, "exists": "", "*": "Timeline of Frodo Baggins"}, {"ns": 0, "exists": "", "*": "Timeline of Galadriel"}, {"ns": 0, "exists": "", "*": "Two Lamps"}, {"ns": 0, "exists": "", "*": "Two Trees of Valinor"}, {"ns": 0, "exists": "", "*": "Utumno"}, {"ns": 0, "exists": "", "*": "Valacirca"}, {"ns": 0, "exists": "", "*": "Valar"}, {"ns": 0, "exists": "", "*": "Valinor"}, {"ns": 0, "exists": "", "*": "Varda"}, {"ns": 0, "exists": "", "*": "War of Wrath"}, {"ns": 0, "exists": "", "*": "War of the Last Alliance"}, {"ns": 0, "exists": "", "*": "War of the Ring"}, {"ns": 0, "exists": "", "*": "Yavanna"}, {"ns": 0, "exists": "", "*": "Years of the Sun"}, {"ns": 0, "exists": "", "*": "Years of the Trees"}, {"ns": 104, "exists": "", "*": "Portal:Timeline"}], "templates": [{"ns": 10, "exists": "", "*": "Template:Section divider"}, {"ns": 10, "exists": "", "*": "Template:Section divider/styles.css"}, {"ns": 10, "exists": "", "*": "Template:Button"}, {"ns": 10, "exists": "", "*": "Template:Button/styles.css"}, {"ns": 10, "exists": "", "*": "Template:Timeline page styles"}, {"ns": 10, "exists": "", "*": "Template:Timeline page styles/styles.css"}, {"ns": 10, "exists": "", "*": "Template:References"}, {"ns": 10, "exists": "", "*": "Template:PM"}, {"ns": 10, "exists": "", "*": "Template:NM"}, {"ns": 10, "exists": "", "*": "Template:L"}], "images": [], "wikitext": {"*": "__NOTOC__\n{| class=\"tg-timeline citizen-overflow\"\n|-\n| rowspan=\"6\" | <div class=\"tg-timeline-end\">[[Music of the Ainur|First Music]]</div>\n| <div class=\"tg-timeline-era\">[[Days before days]]</div>\n| colspan=\"2\" | <div class=\"tg-timeline-era\">[[Years of the Trees]]</div>\n| colspan=\"5\" | <div class=\"tg-timeline-era\">[[Years of the Sun]]</div>\n| rowspan=\"6\"  | <div class=\"tg-timeline-end\">[[Second Music of the Ainur|Second Music]]</div>\n|-\n| <div class=\"tg-timeline-year\">V.Y. 1 – 3500</div>\n| <div class=\"tg-timeline-year\">Y.T. 1 – 1500</div>\n| colspan=\"2\" | <div class=\"tg-timeline-year\">Y.T. 1050 – Y.S. 590</div>\n| <div class=\"tg-timeline-year\">S.A. 1 – 3441</div>\n| <div class=\"tg-timeline-year\">T.A. 1 – 3021</div>\n| <div class=\"tg-timeline-year\">F.A. 1 – c. 2500<ref>{{PM|Third}}, pp. 244-5: \"''Of [[Eldarion]] son of [[Aragorn|Elessar]] it was foretold that he should rule [[Reunited Kingdom|a great realm]], and that '''it should endure for a hundred generations of Men after him, that is until a new age brought in again new things'''…''\"</ref><ref>{{NM|P1vi}}, ''Notes'', Note 30, p. 43</ref></div>\n| <div class=\"tg-timeline-year\">Up to present day<ref>{{L|211}}, ''footnote'', p. 283</ref><ref>{{NM|P1vi}}, p. 39</ref></div>\n|-\n|<div class=\"tg-timeline-title\">[[Days before days]]</div>\n|<div class=\"tg-timeline-title\">[[Years of the Trees]]</div>\n| colspan=\"2\" |<div class=\"tg-timeline-title\">[[First Age]]</div>\n|<div class=\"tg-timeline-title\">[[Second Age]]</div>\n|<div class=\"tg-timeline-title\">[[Third Age]]</div>\n|<div class=\"tg-timeline-title\">[[Fourth Age]]</div>\n|<div class=\"tg-timeline-title\">[[Later Ages]]</div>\n|-\n|{{Section divider|Key events}}\n|{{Section divider|Key events}}\n| colspan=\"2\" |{{Section divider|Key events}}\n|{{Section divider|Key events}}\n|{{Section divider|Key events}}\n|{{Section divider|Key events}}\n|{{Section divider|Key events}}\n|-\n|\n*The [[Valar]] and [[Maiar]] enter [[Arda]]\n*The [[First War]] and the [[Arda Marred|Marring]] of [[Arda]]\n*The [[Spring of Arda]]\n*[[Morgoth|Melkor]] raises the [[Iron Mountains]] and delves [[Utumno]]\n*The [[Two Lamps]] are destroyed\n*The separation of [[Aman]] from [[Middle-earth]]; foundation of [[Valinor]]\n|\n*[[Yavanna]] grows the [[Two Trees of Valinor|Two Trees]] in Valinor\n*[[Aulë]] creates the [[Fathers of the Dwarves|Seven Fathers]] of the [[Dwarves]]\n*[[Manwë]] and Yavanna devise the [[Eagles]] and the [[Ents]] respectively\n*[[Varda]] fashions new [[Stars]] and puts the [[Valacirca]] in the North\n*The [[Darkening of Valinor]]\n| colspan=\"2\" |\n*The [[Awakening of the Elves|Awakening]] of the [[Elves]] by [[Cuiviénen]] and the [[Great Journey|Great March]] of the [[Eldar]]\n*The [[Battle of the Powers]] and the [[Chaining of Melkor]]\n*[[Fëanor]] creates the [[Silmarils]]\n*The [[Battles of Beleriand|War of the Great Jewels]]\n*The [[Awakening of Men|Awakening]] of [[Men]] in [[Hildórien]]\n*The final defeat of [[Morgoth]] in the [[War of Wrath]]\n|\n*The [[Dúnedain]] settle on the [[Elenna|isle]] of [[Númenor]]\n*The [[Rings of Power]] are forged and distributed\n*The appearance of the [[Nazgûl]]\n*The [[Downfall of Númenor]] and the [[Changing of the World]]\n*[[Arnor]] and [[Gondor]] are founded in Middle-earth\n*The [[War of the Last Alliance]]\n|\n*[[The One Ring]] is lost in the waters of [[Anduin]]\n*The [[Angmar War|destruction]] of the Kingdom of Arnor\n*The [[House of Anárion|Line of Kings]] in Gondor breaks\n*[[Sauron]] is defeated in the [[War of the Ring]]\n*The [[Three Rings]] lost their powers forever\n|\n*The beginning of the [[Dominion of Men]] in Middle-earth\n*The [[Thain's Book]] is commissioned by [[Aragorn|King Elessar]]\n*The [[Fourth Age 120|death of King Elessar]] and the ascension of his son [[Eldarion]]\n*[[Durin VII]] is born and retakes [[Moria|Khazad-dûm]] for [[Durin's Folk]]\n*The [[Last Ship]] of the Elves sails into the [[Aman|West]]\n|\n*The Fifth Age\n*The Sixth Age\n*The Seventh Age\n*The [[Dagor Dagorath]] and the End of the World\n|-\n| {{Button|label=View full timeline|page=Timeline/Days before days|type=secondary}}\n| {{Button|label=View full timeline|page=Timeline/Years of the Trees|type=secondary}}\n| colspan=\"2\" | {{Button|label=View full timeline|page=Timeline/First Age|type=secondary}}\n| {{Button|label=View full timeline|page=Timeline/Second Age|type=secondary}}\n| {{Button|label=View full timeline|page=Timeline/Third Age|type=secondary}}\n| {{Button|label=View full timeline|page=Timeline/Fourth Age|type=secondary}}\n| \n|- \n| style=\"width: 2rem;\" |\n| style=\"width: calc(var(--tg-timeline-column-width)*4);\" |\n| style=\"width: calc(var(--tg-timeline-column-width)*4);\" |\n| style=\"width: calc(var(--tg-timeline-column-width)*2);\" |\n| style=\"width: calc(var(--tg-timeline-column-width)*2);\" |\n| style=\"width: calc(var(--tg-timeline-column-width)*4);\" |\n| style=\"width: calc(var(--tg-timeline-column-width)*4);\" |\n| style=\"width: calc(var(--tg-timeline-column-width)*4);\" |\n| style=\"width: calc(var(--tg-timeline-column-width)*4);\" |\n| style=\"width: 2rem;\" |\n|}{{Timeline page styles}}\n\n==See also==\n*[[Portal:Timeline|Timeline Portal]]\n*[[History of Arda]]\n*[[Timeline of Aragorn]]\n*[[Timeline of Frodo Baggins]]\n*[[Timeline of Galadriel]]\n\n[[Category:Timelines|00]]\n\n{{references}}"}}}