{"parse": {"title": "Dave Wittenberg", "pageid": 19485, "redirects": [], "links": [{"ns": 0, "exists": "", "*": "1971"}, {"ns": 0, "exists": "", "*": "1 September"}, {"ns": 0, "exists": "", "*": "2003"}, {"ns": 0, "exists": "", "*": "2006"}, {"ns": 0, "exists": "", "*": "EA's The Battle for Middle-earth II"}, {"ns": 0, "exists": "", "*": "Gollum"}, {"ns": 0, "exists": "", "*": "Gorkil"}, {"ns": 0, "exists": "", "*": "The Lord of the Rings: The Battle for Middle-earth II"}, {"ns": 0, "exists": "", "*": "The Lord of the Rings: The Battle for Middle-earth II: The Rise of the Witch-king"}, {"ns": 0, "exists": "", "*": "The Lord of the Rings: War of the Ring"}], "templates": [{"ns": 10, "exists": "", "*": "Template:Actor"}, {"ns": 10, "exists": "", "*": "Template:Infobox image row"}, {"ns": 10, "exists": "", "*": "Template:Infobox row"}, {"ns": 10, "exists": "", "*": "Template:Infobox/styles.css"}, {"ns": 10, "exists": "", "*": "Template:WP"}], "images": [], "wikitext": {"*": "{{actor\n| image=\n| name=Dave Wittenberg\n| lifetime=[[1 September|September 1]], [[1971]]\n| played=[[Gorkil]]\n| film=''[[EA's The Battle for Middle-earth II]]'' \n| played2=[[Gollum]]\n| film2=''[[The Lord of the Rings: War of the Ring]]''\n| imdb=[http://www.imdb.com/name/nm1043186/ Profile]\n}}\n'''David Richard Paul Wittenberg''' (1971) is an American voice actor. \n\n==Roles==\n* [[2006]] - ''[[The Lord of the Rings: The Battle for Middle-earth II: The Rise of the Witch-king]]'' - Additional voices\n* [[2006]] - ''[[The Lord of the Rings: The Battle for Middle-earth II]]'' - [[Gorkil]], Additional voices\n* [[2003]] - ''[[The Lord of the Rings: War of the Ring]]'' - [[Gollum]]\n\n==External links==\n* '''[http://www.davewittenberg.com/ Official website]'''\n* {{WP|Dave Wittenberg}}\n* [http://voicechasers.com/database/showactor.php?actorid=2754 Dave Wittenberg] at [http://voicechasers.com IMDb]\n\n[[Category:Actors and actresses|Wittenberg, Dave]]\n[[Category:American people|Wittenberg, Dave]]\n[[Category:People by name|Wittenberg, Dave]]"}}}