{"parse": {"title": "Elessar (disambiguation)", "pageid": 2110, "redirects": [{"from": "Elessar", "to": "Elessar (disambiguation)"}], "links": [{"ns": 0, "exists": "", "*": "Aragorn"}, {"ns": 0, "exists": "", "*": "Elessar of Eärendil"}, {"ns": 0, "exists": "", "*": "First Age"}, {"ns": 0, "exists": "", "*": "Quenya"}, {"ns": 0, "exists": "", "*": "The Elessar"}, {"ns": 0, "exists": "", "*": "The History of Galadriel and Celeborn"}, {"ns": 0, "exists": "", "*": "Third Age"}, {"ns": 0, "exists": "", "*": "Tolkien Gateway"}, {"ns": 0, "exists": "", "*": "Unfinished Tales"}, {"ns": 4, "exists": "", "*": "Tolkien Gateway:Naming policy"}], "templates": [{"ns": 10, "exists": "", "*": "Template:Disambig"}], "images": ["Disambig.png"], "wikitext": {"*": "'''Elessar''' (\"Elf-stone\" in [[Quenya]]) can refer to:\n\n* The '''[[Elessar of Eärendil]]''', two fabled gems, one of the [[First Age]] and one of the [[Third Age]].\n* '''King [[Aragorn|Elessar]]''', originally known as Aragorn II.\n\n*\"[[The Elessar]]\", a section in the chapter \"[[The History of Galadriel and Celeborn]]\" in ''[[Unfinished Tales]]''.\n\n{{disambig}}\n[[de:Elessar]]\n[[fr:encyclo/homonymes/elessar]]\n[[fi:Elessar]]"}}}