{"parse": {"title": "Tolkien's Middle-earth", "pageid": 44608, "redirects": [], "links": [{"ns": 6, "exists": "", "*": "File:Tolkien's Middle-earth.jpg"}, {"ns": 0, "exists": "", "*": "1993"}, {"ns": 0, "exists": "", "*": "HarperCollins"}, {"ns": 0, "exists": "", "*": "John Howe"}, {"ns": 0, "exists": "", "*": "Middle-earth"}], "templates": [{"ns": 10, "exists": "", "*": "Template:Book"}, {"ns": 10, "exists": "", "*": "Template:Infobox image row"}, {"ns": 10, "exists": "", "*": "Template:Infobox row"}, {"ns": 10, "*": "Template:Usablenext"}, {"ns": 10, "exists": "", "*": "Template:Infobox/styles.css"}, {"ns": 10, "exists": "", "*": "Template:Title"}, {"ns": 828, "exists": "", "*": "Module:Paramvalidate"}, {"ns": 828, "exists": "", "*": "Module:Arguments"}], "images": ["Tolkien's_Middle-earth.jpg"], "wikitext": {"*": "{{book\n|title=Tolkien's Middle-earth: A Book of 20 Postcards\n| image = Tolkien's Middle-earth.jpg\n|illustrator=[[John Howe]] (cover) \n|publisher=[[HarperCollins]]\n|date=[[1993]]\n|format=Softcover\n|pages=\n|isbn=0-261-10306-7\n}}\n'''''Tolkien's Middle-earth: A Book of 20 Postcards'''''  is a book containing postcards with illustrations inspired by [[Middle-earth]].\n\n==From the back==\n\nA book of 20 postcards featuring the landscapes and cities of Tolkien's magical world. Artists include John Howe, Roger Garland, Alan Lee and Ted Nasmith.\n{{title|italics}}\n[[Category:Postcard books]]\n[[Category:Publications by title]]"}}}