{"parse": {"title": "A Guide to Playing The Hobbit", "pageid": 35585, "redirects": [], "links": [{"ns": 6, "exists": "", "*": "File:A Guide to Playing The Hobbit.png"}, {"ns": 0, "exists": "", "*": "1984"}, {"ns": 0, "exists": "", "*": "2011"}, {"ns": 0, "exists": "", "*": "4 August"}, {"ns": 0, "exists": "", "*": "David Elkan"}, {"ns": 0, "exists": "", "*": "Melbourne House"}, {"ns": 0, "exists": "", "*": "The Hobbit (1982 video game)"}], "templates": [{"ns": 10, "exists": "", "*": "Template:Book"}, {"ns": 10, "exists": "", "*": "Template:Infobox image row"}, {"ns": 10, "exists": "", "*": "Template:Infobox row"}, {"ns": 10, "*": "Template:Usablenext"}, {"ns": 10, "exists": "", "*": "Template:Infobox/styles.css"}, {"ns": 10, "exists": "", "*": "Template:References"}, {"ns": 10, "exists": "", "*": "Template:Amazon"}, {"ns": 10, "exists": "", "*": "Template:Title"}, {"ns": 828, "exists": "", "*": "Module:Paramvalidate"}, {"ns": 828, "exists": "", "*": "Module:Arguments"}], "images": ["A_Guide_to_Playing_The_Hobbit.png"], "wikitext": {"*": "{{book\n|title=A Guide to Playing The Hobbit\n|image=A Guide to Playing The Hobbit.png\n|author=[[David Elkan]]\n|publisher=[[Melbourne House|Melbourne House Publishers, Limited.]]\n|date=[[1984]]\n|format=Paperback\n|pages=76\n|isbn=0861611616\n|}}\n'''''A Guide to Playing The Hobbit''''' is a book by [[David Elkan]] with the aim of helping and guiding players of [[The Hobbit (1982 video game)|the video game adaptation of ''The Hobbit'']] through the game.<ref>[http://books.google.com/books?id=ynFQAQAACAAJ&dq=isbn:0861611616&hl=nl&ei=fL06ToB8iIb7BqHJgOQN&sa=X&oi=book_result&ct=result&resnum=1&ved=0CCkQ6AEwAA A Guide to Playing the Hobbit], [http://books.google.com/books?hl=en Google Books] (accessed at [[4 August]], [[2011]])</ref><ref>[http://www.worldofspectrum.org/infoseekid.cgi?id=2000171 Guide to Playing The Hobbit, A] at [[wikipedia:World of Spectrum|World of Spectrum]] (accessed at [[4 August]], [[2011]])</ref>\n\n{{references}}\n\n==External links==\n* {{Amazon}}\n{{title|italics}}\n{{DEFAULTSORT:Guide to Playing The Hobbit, A}}\n[[Category:Books about video games]]\n[[Category:Publications by title]]"}}}