{"parse": {"title": "Ausa", "pageid": 30846, "redirects": [{"from": "Auþa", "to": "Ausa"}], "links": [{"ns": 0, "exists": "", "*": "Auth"}, {"ns": 0, "exists": "", "*": "Carl F. Hostetter"}, {"ns": 0, "exists": "", "*": "Common Eldarin"}, {"ns": 0, "exists": "", "*": "Elvish"}, {"ns": 0, "exists": "", "*": "Gwath"}, {"ns": 0, "exists": "", "*": "J.R.R. Tolkien"}, {"ns": 0, "exists": "", "*": "Primitive Quendian"}, {"ns": 0, "exists": "", "*": "Quenya"}, {"ns": 0, "exists": "", "*": "Sindarin"}, {"ns": 0, "exists": "", "*": "Spectres"}, {"ns": 0, "exists": "", "*": "Sundocarme"}, {"ns": 0, "exists": "", "*": "The Rivers and Beacon-hills of Gondor"}, {"ns": 0, "exists": "", "*": "Vinyar Tengwar 42"}, {"ns": 0, "exists": "", "*": "WATH"}], "templates": [{"ns": 10, "exists": "", "*": "Template:References"}, {"ns": 10, "exists": "", "*": "Template:VT"}, {"ns": 10, "exists": "", "*": "Template:Title"}], "images": [], "wikitext": {"*": "'''''ausa''''' (or ''auþa'') is a [[Quenya]] word meaning \"a dim shape, [[Spectres|spectral]] or vague apparition\".<ref name=VT42>{{VT|42a}}, pp. 9-10</ref>\n\n==Etymology==\n\n*[[Elvish]] ([[Primitive Quendian]] or [[Common Eldarin]]) ''aw'tha'' (from [[Sundocarme|root]] [[WATH]])<ref name=VT42/>\n\n==Cognates==\n\n*[[Sindarin]] ''[[auth]]''\n*[[Sindarin]] ''[[gwath]]''\n\n==See also==\n*[[Spectres]]\n{{references}}\n{{title|lowercase}}\n[[Category:Quenya nouns]]"}}}